Workbook

Sheet Read Me
A1: Shoe Inventory Data Source Simulation
A2: Mock athletic / sport / casual footwear inventory across four store locations
A4: Purpose
A5: This workbook is a synthetic data source built to stand in for a real footwear inventory extract during design, demo, and integration testing. Every SKU, UPC, quantity, and store number in it is fabricated. It is not Hibbett data and carries no confidential information.
A7: Sheets
A8: Inventory Master — the fact table. One row per SKU (style / color / size), with on-hand units for each of the four stores.
A9: Style Master — the dimension table. One row per style-colorway, with the SKU count and total units rolled up by formula.
A10: Store Directory — the four store locations, their attributes, and their assortment / stocking profile.
A11: Store Summary — live SUMIFS roll-ups of units and retail value by brand and by category, per store.
A13: How to read the store columns
A14: A number (including 0) means the store is assorted for that SKU. 0 = assorted but currently out of stock.
A15: A blank cell means the store does not carry that SKU at all — it is not part of that store's assortment.
... A42: Sales Floor Units, Overstock Location, and Last Counted are generated values, not formulas. Overstock locations are only assigned where back room depth is six pairs or more.

Sheet Store Directory
A1: Store Directory
A3: Store Number | B3: Store Name | C3: City | D3: State | E3: Region | F3: Banner / Format | G3: Selling Sq Ft | H3: Date Opened | I3: Volume Index | J3: Assortment Depth | K3: SKUs Assorted | L3: Units On Hand | M3: On-Hand Retail Value
A4: 0146 | B4: Trussville Marketplace | C4: Trussville | D4: AL | E4: AL / North | F4: Hibbett Sports | G4: 5200 | H4: 40620 | I4: 1 | J4: Core chain assortment | K4: =COUNT('Inventory Master'!$T$2:$T$525) -> 443 | L4: =SUM('Inventory Master'!$T$2:$T$525) -> 1152 | M4: =SUMPRODUCT('Inventory Master'!$R$2:$R$525,'Inventory Master'!$T$2:$T$525) -> 128139.48
A5: 1382 | B5: Cartersville Pavilion | C5: Cartersville | D5: GA | E5: GA / Northwest | F5: Hibbett Sports | G5: 4400 | H5: 41853 | I5: 0.7 | J5: Reduced size runs | K5: =COUNT('Inventory Master'!$U$2:$U$525) -> 342 | L5: =SUM('Inventory Master'!$U$2:$U$525) -> 663 | M5: =SUMPRODUCT('Inventory Master'!$R$2:$R$525,'Inventory Master'!$U$2:$U$525) -> 75894.37
A6: 2071 | B6: Southaven Towne Center | C6: Southaven | D6: MS | E6: MS / Memphis Metro | F6: City Gear | G6: 6800 | H6: 40110 | I6: 1.35 | J6: Flagship / full depth | K6: =COUNT('Inventory Master'!$V$2:$V$525) -> 514 | L6: =SUM('Inventory Master'!$V$2:$V$525) -> 1831 | M6: =SUMPRODUCT('Inventory Master'!$R$2:$R$525,'Inventory Master'!$V$2:$V$525) -> 202513.69
A7: 3719 | B7: Florence Regency Square | C7: Florence | D7: SC | E7: SC / Pee Dee | F7: Hibbett Sports | G7: 3900 | H7: 43231 | I7: 0.55 | J7: Small-market, edited | K7: =COUNT('Inventory Master'!$W$2:$W$525) -> 248 | L7: =SUM('Inventory Master'!$W$2:$W$525) -> 375 | M7: =SUMPRODUCT('Inventory Master'!$R$2:$R$525,'Inventory Master'!$W$2:$W$525) -> 39906.25
A8: TOTAL | K8: =SUM(K4:K7) -> 1547 | L8: =SUM(L4:L7) -> 4021 | M8: =SUM(M4:M7) -> 446453.79
A10: SKUs Assorted counts store cells that contain a number (0 included); a blank means the SKU is not carried at that store. Volume Index is the relative on-hand depth multiplier used to generate the data.

Sheet Inventory Master
A1: SKU | B1: UPC | C1: Item ID | D1: Manufacturer | E1: Brand | F1: Model | G1: Style Number | H1: Product Description | I1: Category | J1: Sub-Category | K1: Gender | L1: Color | M1: Size | N1: Width | O1: Season | P1: Lifecycle Status | Q1: MSRP | R1: Current Retail | S1: Unit Cost | T1: Store 0146 On Hand | U1: Store 1382 On Hand | V1: Store 2071 On Hand | W1: Store 3719 On Hand | X1: Total On Hand | Y1: Stores Stocking | Z1: On-Hand Retail Value | AA1: Last Received
A2: HB-4102582 | B2: 877862873808 | C2: ITM-700225 | D2: adidas AG | E2: adidas | F2: Adilette Comfort Slide | G2: AU7200 | H2: adidas Adilette Comfort Slide "Core Black/White" Men's Shoe | I2: Sandals | J2: Slides | K2: Men | L2: Core Black/White | M2: 13 | N2: D - Medium | O2: FA26 | P2: Active | Q2: 34.99 | R2: 34.99 | S2: 19.22 | T2: 3 | U2: 0 | V2: 5 | X2: =SUM(T2:W2) -> 8 | Y2: =COUNT(T2:W2) -> 3 | Z2: =R2*X2 -> 279.92 | AA2: 46212
A3: HB-4100776 | B3: 817439334285 | C3: ITM-700140 | D3: Nike, Inc. | E3: Nike | F3: Revolution 7 | G3: TA0814-787 | H3: Nike Revolution 7 "Black/Off Noir/Dark Smoke Grey" Men's Shoe | I3: Running | J3: Entry Cushion | K3: Men | L3: Black/Off Noir/Dark Smoke Grey | M3: 12 | N3: D - Medium | O3: SP26 | P3: Active | Q3: 74.99 | R3: 74.99 | S3: 36.3 | T3: 0 | V3: 2 | X3: =SUM(T3:W3) -> 2 | Y3: =COUNT(T3:W3) -> 2 | Z3: =R3*X3 -> 149.98 | AA3: 46212
A4: HB-4103107 | B4: 840252722072 | C4: ITM-700247 | D4: New Balance Athletics, Inc. | E4: New Balance | F4: Fresh Foam Arishi v4 | G4: W8600KRG | H4: New Balance Fresh Foam Arishi v4 "Black/Silver" Men's Shoe | I4: Running | J4: Entry Cushion | K4: Men | L4: Black/Silver | M4: 11.5 | N4: D - Medium | O4: FA26 | P4: Active | Q4: 79.99 | R4: 79.99 | S4: 39.84 | T4: 2 | V4: 3 | X4: =SUM(T4:W4) -> 5 | Y4: =COUNT(T4:W4) -> 2 | Z4: =R4*X4 -> 399.95 | AA4: 46147
A5: HB-4103370 | B5: 824027160113 | C5: ITM-700264 | D5: Under Armour, Inc. | E5: Under Armour | F5: Surge 4 | G5: 3021004-318 | H5: Under Armour Surge 4 "Black/Red" Big Kids' Shoe | I5: Running | J5: Entry Cushion | K5: Big Kids | L5: Black/Red | M5: 5Y | N5: M - Medium | O5: SP26 | P5: Active | Q5: 64.99 | R5: 64.99 | S5: 32.11 | V5: 3 | X5: =SUM(T5:W5) -> 3 | Y5: =COUNT(T5:W5) -> 1 | Z5: =R5*X5 -> 194.97 | AA5: 46174
A6: HB-4101994 | B6: 811910052093 | C6: ITM-700194 | D6: adidas AG | E6: adidas Originals | F6: Handball Spezial | G6: YN8777 | H6: adidas Originals Handball Spezial "Blue/Gum" Men's Shoe | I6: Casual | J6: Terrace / Lifestyle | K6: Men | L6: Blue/Gum | M6: 9 | N6: D - Medium | O6: SU26 | P6: Active | Q6: 109.99 | R6: 109.99 | S6: 54.53 | T6: 2 | U6: 4 | V6: 3 | W6: 3 | X6: =SUM(T6:W6) -> 12 | Y6: =COUNT(T6:W6) -> 4 | Z6: =R6*X6 -> 1319.88 | AA6: 46142
A7: HB-4104772 | B7: 864758033155 | C7: ITM-700349 | D7: Mizuno Corporation | E7: Mizuno | F7: Ambition 4 Turf | G7: 212707-7648 | H7: Mizuno Ambition 4 Turf "Navy/White" Men's Shoe | I7: Baseball | J7: Turf Trainer | K7: Men | L7: Navy/White | M7: 9.5 | N7: D - Medium | O7: SU26 | P7: Active | Q7: 89.99 | R7: 89.99 | S7: 44.22 | T7: 3 | U7: 0 | V7: 7 | X7: =SUM(T7:W7) -> 10 | Y7: =COUNT(T7:W7) -> 3 | Z7: =R7*X7 -> 899.9 | AA7: 46142
A8: HB-4105167 | B8: 886681888719 | C8: ITM-700373 | D8: VF Corporation | E8: Vans | F8: Knu Skool | G8: VN000FMD01V | H8: Vans Knu Skool "Navy/White" Women's Shoe | I8: Casual | J8: Canvas / Skate | K8: Women | L8: Navy/White | M8: 8.5 | N8: B - Medium | O8: SP26 | P8: Active | Q8: 89.99 | R8: 89.99 | S8: 45.49 | T8: 4 | U8: 0 | V8: 4 | X8: =SUM(T8:W8) -> 8 | Y8: =COUNT(T8:W8) -> 3 | Z8: =R8*X8 -> 719.92 | AA8: 46111
A9: HB-4105459 | B9: 861021087424 | C9: ITM-700388 | D9: Crocs, Inc. | E9: Crocs | F9: Classic Clog | G9: 57800-178 | H9: Crocs Classic Clog "Bubblegum Pink" Little Kids' Shoe | I9: Sandals | J9: Clogs | K9: Little Kids | L9: Bubblegum Pink | M9: 2Y | N9: M - Medium | O9: FA26 | P9: Pre-Season | Q9: 44.99 | R9: 44.99 | S9: 22.09 | T9: 3 | U9: 5 | V9: 4 | W9: 6 | X9: =SUM(T9:W9) -> 18 | Y9: =COUNT(T9:W9) -> 4 | Z9: =R9*X9 -> 809.82 | AA9: 46188
A10: HB-4105056 | B10: 848859341885 | C10: ITM-700366 | D10: VF Corporation | E10: Vans | F10: Classic Slip-On | G10: VN000TBP59A | H10: Vans Classic Slip-On "Black/White Checkerboard" Unisex Shoe | I10: Casual | J10: Canvas / Skate | K10: Unisex | L10: Black/White Checkerboard | M10: 10 | N10: M - Medium | O10: SP26 | P10: Active | Q10: 69.99 | R10: 69.99 | S10: 37.84 | T10: 4 | U10: 2 | V10: 4 | W10: 0 | X10: =SUM(T10:W10) -> 10 | Y10: =COUNT(T10:W10) -> 4 | Z10: =R10*X10 -> 699.9 | AA10: 46086
A11: HB-4100422 | B11: 870774071458 | C11: ITM-700117 | D11: Nike, Inc. | E11: Nike | F11: Air Max Dn | G11: JK3828-236 | H11: Nike Air Max Dn "Black/Metallic Silver" Men's Shoe | I11: Casual | J11: Tech Running | K11: Men | L11: Black/Metallic Silver | M11: 13 | N11: D - Medium | O11: SU26 | P11: Active | Q11: 169.99 | R11: 169.99 | S11: 82.49 | V11: 4 | X11: =SUM(T11:W11) -> 4 | Y11: =COUNT(T11:W11) -> 1 | Z11: =R11*X11 -> 679.96 | AA11: 46048
A12: HB-4101174 | B12: 802956043183 | C12: ITM-700156 | D12: Nike, Inc. | E12: Nike | F12: Kobe 5 Protro | G12: MX1318-449 | H12: Nike Kobe 5 Protro "White/Varsity Purple" Men's Shoe | I12: Basketball | J12: Retro Performance | K12: Men | L12: White/Varsity Purple | M12: 10 | N12: D - Medium | O12: SU26 | P12: Active | Q12: 199.99 | R12: 199.99 | S12: 102.88 | T12: 5 | U12: 1 | V12: 5 | W12: 2 | X12: =SUM(T12:W12) -> 13 | Y12: =COUNT(T12:W12) -> 4 | Z12: =R12*X12 -> 2599.87 | AA12: 46101
A13: HB-4100490 | B13: 865594518943 | C13: ITM-700120 | D13: Nike, Inc. | E13: Nike | F13: Dunk Low | G13: YF5377-998 | H13: Nike Dunk Low "Midnight Navy/White" Big Kids' Shoe | I13: Casual | J13: Court / Lifestyle | K13: Big Kids | L13: Midnight Navy/White | M13: 4.5Y | N13: M - Medium | O13: HO25 | P13: Clearance | Q13: 94.99 | R13: 65.99 | S13: 47.59 | T13: 6 | V13: 4 | W13: 3 | X13: =SUM(T13:W13) -> 13 | Y13: =COUNT(T13:W13) -> 3 | Z13: =R13*X13 -> 857.87 | AA13: 46079
A14: HB-4102807 | B14: 837917925775 | C14: ITM-700230 | D14: New Balance Athletics, Inc. | E14: New Balance | F14: 9060 | G14: U1951JZR | H14: New Balance 9060 "Rain Cloud/Grey Matter" Men's Shoe | I14: Casual | J14: Retro Running | K14: Men | L14: Rain Cloud/Grey Matter | M14: 12 | N14: D - Medium | O14: HO25 | P14: Clearance | Q14: 149.99 | R14: 89.99 | S14: 74.84 | U14: 5 | V14: 3 | X14: =SUM(T14:W14) -> 8 | Y14: =COUNT(T14:W14) -> 2 | Z14: =R14*X14 -> 719.92 | AA14: 46155
A15: HB-4103772 | B15: 824165626004 | C15: ITM-700282 | D15: PUMA SE | E15: PUMA | F15: RS-X Efekt | G15: 832747-45 | H15: PUMA RS-X Efekt "White/Vapor Grey" Men's Shoe | I15: Casual | J15: Chunky Lifestyle | K15: Men | L15: White/Vapor Grey | M15: 11 | N15: D - Medium | O15: SU26 | P15: Active | Q15: 119.99 | R15: 119.99 | S15: 66.31 | T15: 4 | U15: 2 | V15: 4 | X15: =SUM(T15:W15) -> 10 | Y15: =COUNT(T15:W15) -> 3 | Z15: =R15*X15 -> 1199.9 | AA15: 46041
A16: HB-4101095 | B16: 888909252745 | C16: ITM-700153 | D16: Nike, Inc. | E16: Nike | F16: Giannis Immortality 4 | G16: RF7597-325 | H16: Nike Giannis Immortality 4 "Black/Green Strike" Big Kids' Shoe | I16: Basketball | J16: Signature | K16: Big Kids | L16: Black/Green Strike | M16: 4.5Y | N16: M - Medium | O16: SU26 | P16: Active | Q16: 84.99 | R16: 84.99 | S16: 46.96 | T16: 0 | U16: 3 | X16: =SUM(T16:W16) -> 3 | Y16: =COUNT(T16:W16) -> 2 | Z16: =R16*X16 -> 254.97 | AA16: 46080
A17: HB-4100541 | B17: 812477168963 | C17: ITM-700122 | D17: Nike, Inc. | E17: Nike | F17: Court Vision Low Next Nature | G17: CC5588-537 | H17: Nike Court Vision Low Next Nature "White/Black" Men's Shoe | I17: Casual | J17: Court / Lifestyle | K17: Men | L17: White/Black | M17: 9.5 | N17: D - Medium | O17: SU26 | P17: Active | Q17: 79.99 | R17: 79.99 | S17: 42.84 | T17: 2 | U17: 1 | V17: 4 | W17: 0 | X17: =SUM(T17:W17) -> 7 | Y17: =COUNT(T17:W17) -> 4 | Z17: =R17*X17 -> 559.93 | AA17: 46147
A18: HB-4102359 | B18: 864084016085 | C18: ITM-700214 | D18: adidas AG | E18: adidas | F18: Ultraboost 5 | G18: BJ7996 | H18: adidas Ultraboost 5 "Core Black/Carbon" Men's Shoe | I18: Running | J18: Neutral Cushion | K18: Men | L18: Core Black/Carbon | M18: 11 | N18: D - Medium | O18: SU26 | P18: Active | Q18: 189.99 | R18: 189.99 | S18: 103.72 | T18: 3 | U18: 1 | V18: 5 | X18: =SUM(T18:W18) -> 9 | Y18: =COUNT(T18:W18) -> 3 | Z18: =R18*X18 -> 1709.91 | AA18: 46168
A19: HB-4101362 | B19: 847434231972 | C19: ITM-700165 | D19: Nike, Inc. | E19: Jordan | F19: Air Jordan 1 Low | G19: TV5434-986 | H19: Jordan Air Jordan 1 Low "White/Sail/Pink" Women's Shoe | I19: Casual | J19: Retro Basketball | K19: Women | L19: White/Sail/Pink | M19: 7.5 | N19: B - Medium | O19: SU26 | P19: Clearance | Q19: 129.99 | R19: 77.99 | S19: 70.91 | V19: 0 | X19: =SUM(T19:W19) -> 0 | Y19: =COUNT(T19:W19) -> 1 | Z19: =R19*X19 -> 0 | AA19: 46133
A20: HB-4103833 | B20: 847077718461 | C20: ITM-700285 | D20: PUMA SE | E20: PUMA | F20: Softride Enzo Evo | G20: 355908-86 | H20: PUMA Softride Enzo Evo "Black/Cool Dark Grey" Men's Shoe | I20: Running | J20: Walking | K20: Men | L20: Black/Cool Dark Grey | M20: 10 | N20: D - Medium | O20: SU26 | P20: Active | Q20: 79.99 | R20: 79.99 | S20: 41.96 | T20: 3 | V20: 5 | W20: 1 | X20: =SUM(T20:W20) -> 9 | Y20: =COUNT(T20:W20) -> 3 | Z20: =R20*X20 -> 719.91 | AA20: 46228
A21: HB-4100877 | B21: 848475416799 | C21: ITM-700145 | D21: Nike, Inc. | E21: Nike | F21: InfinityRN 4 | G21: NT6349-799 | H21: Nike InfinityRN 4 "Barely Grape/Lilac" Women's Shoe | I21: Running | J21: Stability | K21: Women | L21: Barely Grape/Lilac | M21: 6.5 | N21: B - Medium | O21: SU26 | P21: Active | Q21: 164.99 | R21: 164.99 | S21: 89.57 | T21: 0 | U21: 0 | V21: 4 | W21: 2 | X21: =SUM(T21:W21) -> 6 | Y21: =COUNT(T21:W21) -> 4 | Z21: =R21*X21 -> 989.94 | AA21: 46060
A22: HB-4103817 | B22: 859579594457 | C22: ITM-700285 | D22: PUMA SE | E22: PUMA | F22: Softride Enzo Evo | G22: 355908-86 | H22: PUMA Softride Enzo Evo "Black/Cool Dark Grey" Men's Shoe | I22: Running | J22: Walking | K22: Men | L22: Black/Cool Dark Grey | M22: 8.5 | N22: D - Medium | O22: SU26 | P22: Active | Q22: 79.99 | R22: 79.99 | S22: 41.96 | T22: 4 | V22: 5 | W22: 1 | X22: =SUM(T22:W22) -> 10 | Y22: =COUNT(T22:W22) -> 3 | Z22: =R22*X22 -> 799.9 | AA22: 46168
A23: HB-4103401 | B23: 837235737479 | C23: ITM-700267 | D23: Under Armour, Inc. | E23: Under Armour | F23: Curry 12 | G23: 3029154-866 | H23: Under Armour Curry 12 "White/Team Royal" Men's Shoe | I23: Basketball | J23: Signature | K23: Men | L23: White/Team Royal | M23: 10 | N23: D - Medium | O23: SU26 | P23: Active | Q23: 169.99 | R23: 169.99 | S23: 86.49 | T23: 0 | U23: 3 | V23: 8 | X23: =SUM(T23:W23) -> 11 | Y23: =COUNT(T23:W23) -> 3 | Z23: =R23*X23 -> 1869.89 | AA23: 46199
A24: HB-4105636 | B24: 889723092906 | C24: ITM-700397 | D24: VF Corporation | E24: Timberland | F24: 6-Inch Premium Waterproof Boot | G24: TB0X6692R | H24: Timberland 6-Inch Premium Waterproof Boot "Wheat Nubuck" Men's Shoe | I24: Casual | J24: Boots | K24: Men | L24: Wheat Nubuck | M24: 10.5 | N24: D - Medium | O24: SP26 | P24: Active | Q24: 209.99 | R24: 209.99 | S24: 110.54 | T24: 5 | V24: 5 | X24: =SUM(T24:W24) -> 10 | Y24: =COUNT(T24:W24) -> 2 | Z24: =R24*X24 -> 2099.9 | AA24: 46037
A25: HB-4104520 | B25: 897745277299 | C25: ITM-700334 | D25: On Holding AG | E25: On | F25: Cloudnova 2 | G25: 307R23993 | H25: On Cloudnova 2 "White/Pearl" Women's Shoe | I25: Casual | J25: Tech Lifestyle | K25: Women | L25: White/Pearl | M25: 7 | N25: B - Medium | O25: SU26 | P25: Active | Q25: 159.99 | R25: 159.99 | S25: 87.47 | T25: 5 | U25: 4 | V25: 7 | X25: =SUM(T25:W25) -> 16 | Y25: =COUNT(T25:W25) -> 3 | Z25: =R25*X25 -> 2559.84 | AA25: 46166
A26: HB-4104364 | B26: 876101334564 | C26: ITM-700317 | D26: Deckers Brands | E26: HOKA | F26: Clifton 10 | G26: 1120932-NARX | H26: HOKA Clifton 10 "Black/White" Men's Shoe | I26: Running | J26: Premium Cushion | K26: Men | L26: Black/White | M26: 10 | N26: D - Medium | O26: SP26 | P26: Active | Q26: 154.99 | R26: 154.99 | S26: 78.28 | T26: 3 | U26: 4 | V26: 3 | W26: 0 | X26: =SUM(T26:W26) -> 10 | Y26: =COUNT(T26:W26) -> 4 | Z26: =R26*X26 -> 1549.9 | AA26: 46185
A27: HB-4104490 | B27: 828913028609 | C27: ITM-700326 | D27: Deckers Brands | E27: HOKA | F27: Arahi 8 | G27: 1150732-UCNK | H27: HOKA Arahi 8 "White/Coastal Sky" Women's Shoe | I27: Running | J27: Stability | K27: Women | L27: White/Coastal Sky | M27: 8 | N27: B - Medium | O27: SU26 | P27: Active | Q27: 154.99 | R27: 154.99 | S27: 85.1 | T27: 0 | U27: 3 | V27: 5 | X27: =SUM(T27:W27) -> 8 | Y27: =COUNT(T27:W27) -> 3 | Z27: =R27*X27 -> 1239.92 | AA27: 46167
A28: HB-4103743 | B28: 854961993890 | C28: ITM-700282 | D28: PUMA SE | E28: PUMA | F28: RS-X Efekt | G28: 832747-45 | H28: PUMA RS-X Efekt "White/Vapor Grey" Men's Shoe | I28: Casual | J28: Chunky Lifestyle | K28: Men | L28: White/Vapor Grey | M28: 10 | N28: D - Medium | O28: SU26 | P28: Active | Q28: 119.99 | R28: 119.99 | S28: 66.31 | T28: 1 | U28: 3 | V28: 5 | X28: =SUM(T28:W28) -> 9 | Y28: =COUNT(T28:W28) -> 3 | Z28: =R28*X28 -> 1079.91 | AA28: 46157
A29: HB-4101369 | B29: 882819340864 | C29: ITM-700165 | D29: Nike, Inc. | E29: Jordan | F29: Air Jordan 1 Low | G29: TV5434-986 | H29: Jordan Air Jordan 1 Low "White/Sail/Pink" Women's Shoe | I29: Casual | J29: Retro Basketball | K29: Women | L29: White/Sail/Pink | M29: 8 | N29: B - Medium | O29: SU26 | P29: Clearance | Q29: 129.99 | R29: 77.99 | S29: 70.91 | V29: 2 | X29: =SUM(T29:W29) -> 2 | Y29: =COUNT(T29:W29) -> 1 | Z29: =R29*X29 -> 155.98 | AA29: 46119
A30: HB-4100524 | B30: 808900209963 | C30: ITM-700120 | D30: Nike, Inc. | E30: Nike | F30: Dunk Low | G30: YF5377-998 | H30: Nike Dunk Low "Midnight Navy/White" Big Kids' Shoe | I30: Casual | J30: Court / Lifestyle | K30: Big Kids | L30: Midnight Navy/White | M30: 5.5Y | N30: M - Medium | O30: HO25 | P30: Clearance | Q30: 94.99 | R30: 65.99 | S30: 47.59 | T30: 2 | V30: 6 | W30: 0 | X30: =SUM(T30:W30) -> 8 | Y30: =COUNT(T30:W30) -> 3 | Z30: =R30*X30 -> 527.92 | AA30: 46224
A31: HB-4103610 | B31: 867246015740 | C31: ITM-700276 | D31: PUMA SE | E31: PUMA | F31: Palermo | G31: 848787-69 | H31: PUMA Palermo "Vapor Grey/Green" Women's Shoe | I31: Casual | J31: Terrace / Lifestyle | K31: Women | L31: Vapor Grey/Green | M31: 7 | N31: B - Medium | O31: FA26 | P31: Active | Q31: 89.99 | R31: 89.99 | S31: 45.15 | T31: 0 | V31: 4 | W31: 0 | X31: =SUM(T31:W31) -> 4 | Y31: =COUNT(T31:W31) -> 3 | Z31: =R31*X31 -> 359.96 | AA31: 46054
A32: HB-4105212 | B32: 870908185389 | C32: ITM-700375 | D32: Reebok International Ltd. | E32: Reebok | F32: Club C 85 | G32: 100029592 | H32: Reebok Club C 85 "White/Green" Men's Shoe | I32: Casual | J32: Court / Lifestyle | K32: Men | L32: White/Green | M32: 9.5 | N32: D - Medium | O32: FA25 | P32: Clearance | Q32: 89.99 | R32: 62.99 | S32: 49.53 | T32: 3 | U32: 2 | V32: 2 | W32: 4 | X32: =SUM(T32:W32) -> 11 | Y32: =COUNT(T32:W32) -> 4 | Z32: =R32*X32 -> 692.89 | AA32: 46226
A33: HB-4103021 | B33: 889320250523 | C33: ITM-700240 | D33: New Balance Athletics, Inc. | E33: New Balance | F33: Fresh Foam X 880v15 | G33: M0214WXX | H33: New Balance Fresh Foam X 880v15 "Black/Lead" Men's Shoe | I33: Running | J33: Neutral Cushion | K33: Men | L33: Black/Lead | M33: 12 | N33: D - Medium | O33: FA26 | P33: Pre-Season | Q33: 149.99 | R33: 149.99 | S33: 72.91 | T33: 5 | U33: 0 | V33: 6 | X33: =SUM(T33:W33) -> 11 | Y33: =COUNT(T33:W33) -> 3 | Z33: =R33*X33 -> 1649.89 | AA33: 46122
A34: HB-4102908 | B34: 865619966345 | C34: ITM-700237 | D34: New Balance Athletics, Inc. | E34: New Balance | F34: 480 | G34: W9114PEW | H34: New Balance 480 "White/Black" Big Kids' Shoe | I34: Casual | J34: Court / Lifestyle | K34: Big Kids | L34: White/Black | M34: 4.5Y | N34: M - Medium | O34: SU26 | P34: Active | Q34: 69.99 | R34: 69.99 | S34: 39.11 | T34: 4 | V34: 5 | X34: =SUM(T34:W34) -> 9 | Y34: =COUNT(T34:W34) -> 2 | Z34: =R34*X34 -> 629.91 | AA34: 46216
A35: HB-4102324 | B35: 839105167645 | C35: ITM-700210 | D35: adidas AG | E35: adidas | F35: Grand Court 2.0 | G35: XZ7710 | H35: adidas Grand Court 2.0 "Cloud White/Pink" Little Kids' Shoe | I35: Casual | J35: Court / Lifestyle | K35: Little Kids | L35: Cloud White/Pink | M35: 3Y | N35: M - Medium | O35: SU26 | P35: Active | Q35: 49.99 | R35: 49.99 | S35: 24.93 | T35: 0 | U35: 0 | V35: 3 | W35: 4 | X35: =SUM(T35:W35) -> 7 | Y35: =COUNT(T35:W35) -> 4 | Z35: =R35*X35 -> 349.93 | AA35: 46120
A36: HB-4104724 | B36: 866164912602 | C36: ITM-700347 | D36: Mizuno Corporation | E36: Mizuno | F36: Wave Rider 29 | G36: 616964-5195 | H36: Mizuno Wave Rider 29 "Black/Silver" Men's Shoe | I36: Running | J36: Neutral Cushion | K36: Men | L36: Black/Silver | M36: 9.5 | N36: D - Medium | O36: SP26 | P36: Active | Q36: 144.99 | R36: 144.99 | S36: 76.41 | T36: 1 | V36: 1 | X36: =SUM(T36:W36) -> 2 | Y36: =COUNT(T36:W36) -> 2 | Z36: =R36*X36 -> 289.98 | AA36: 46175
A37: HB-4103090 | B37: 807411451217 | C37: ITM-700247 | D37: New Balance Athletics, Inc. | E37: New Balance | F37: Fresh Foam Arishi v4 | G37: W8600KRG | H37: New Balance Fresh Foam Arishi v4 "Black/Silver" Men's Shoe | I37: Running | J37: Entry Cushion | K37: Men | L37: Black/Silver | M37: 10.5 | N37: D - Medium | O37: FA26 | P37: Active | Q37: 79.99 | R37: 79.99 | S37: 39.84 | T37: 5 | V37: 4 | X37: =SUM(T37:W37) -> 9 | Y37: =COUNT(T37:W37) -> 2 | Z37: =R37*X37 -> 719.91 | AA37: 46161
A38: HB-4102684 | B38: 819754951796 | C38: ITM-700227 | D38: New Balance Athletics, Inc. | E38: New Balance | F38: 574 Core | G38: M2807JKW | H38: New Balance 574 Core "Grey/White" Men's Shoe | I38: Casual | J38: Retro Running | K38: Men | L38: Grey/White | M38: 10 | N38: D - Medium | O38: HO25 | P38: Clearance | Q38: 89.99 | R38: 53.99 | S38: 46.24 | T38: 4 | U38: 2 | V38: 3 | W38: 1 | X38: =SUM(T38:W38) -> 10 | Y38: =COUNT(T38:W38) -> 4 | Z38: =R38*X38 -> 539.9 | AA38: 46218
A39: HB-4100045 | B39: 882027918718 | C39: ITM-700104 | D39: Nike, Inc. | E39: Nike | F39: Air Force 1 '07 | G39: ZT6343-223 | H39: Nike Air Force 1 '07 "White/White" Men's Shoe | I39: Casual | J39: Court / Lifestyle | K39: Men | L39: White/White | M39: 9.5 | N39: D - Medium | O39: SP26 | P39: Active | Q39: 124.99 | R39: 124.99 | S39: 68.25 | T39: 1 | U39: 1 | V39: 5 | X39: =SUM(T39:W39) -> 7 | Y39: =COUNT(T39:W39) -> 3 | Z39: =R39*X39 -> 874.93 | AA39: 46126
A40: HB-4105384 | B40: 871010395227 | C40: ITM-700385 | D40: Skechers U.S.A., Inc. | E40: Skechers | F40: Arch Fit 2.0 | G40: 215286-HPF | H40: Skechers Arch Fit 2.0 "Grey/Navy" Men's Shoe | I40: Running | J40: Walking | K40: Men | L40: Grey/Navy | M40: 11 | N40: D - Medium | O40: SU26 | P40: Active | Q40: 99.99 | R40: 99.99 | S40: 55.37 | T40: 3 | V40: 2 | W40: 4 | X40: =SUM(T40:W40) -> 9 | Y40: =COUNT(T40:W40) -> 3 | Z40: =R40*X40 -> 899.91 | AA40: 46103
A41: HB-4105696 | B41: 824414265967 | C41: ITM-700402 | D41: Birkenstock GmbH | E41: Birkenstock | F41: Arizona Essentials EVA | G41: 4242715 | H41: Birkenstock Arizona Essentials EVA "Black" Unisex Shoe | I41: Sandals | J41: Sandals | K41: Unisex | L41: Black | M41: 5 | N41: M - Medium | O41: HO25 | P41: Active | Q41: 54.99 | R41: 54.99 | S41: 26.61 | T41: 3 | V41: 0 | X41: =SUM(T41:W41) -> 3 | Y41: =COUNT(T41:W41) -> 2 | Z41: =R41*X41 -> 164.97 | AA41: 46035
A42: HB-4101592 | B42: 894384860846 | C42: ITM-700177 | D42: Nike, Inc. | E42: Jordan | F42: Air Jordan 13 Retro | G42: YD8499-570 | H42: Jordan Air Jordan 13 Retro "Black/Gym Red" Big Kids' Shoe | I42: Casual | J42: Retro Basketball | K42: Big Kids | L42: Black/Gym Red | M42: 7Y | N42: M - Medium | O42: FA26 | P42: Active | Q42: 154.99 | R42: 154.99 | S42: 85.71 | T42: 4 | V42: 0 | W42: 2 | X42: =SUM(T42:W42) -> 6 | Y42: =COUNT(T42:W42) -> 3 | Z42: =R42*X42 -> 929.94 | AA42: 46198
A43: HB-4103908 | B43: 884068968272 | C43: ITM-700286 | D43: PUMA SE | E43: PUMA | F43: Caven 2.0 | G43: 959067-43 | H43: PUMA Caven 2.0 "White/Navy" Little Kids' Shoe | I43: Casual | J43: Court / Lifestyle | K43: Little Kids | L43: White/Navy | M43: 3Y | N43: M - Medium | O43: FA25 | P43: Clearance | Q43: 44.99 | R43: 33.99 | S43: 24.11 | V43: 0 | X43: =SUM(T43:W43) -> 0 | Y43: =COUNT(T43:W43) -> 1 | Z43: =R43*X43 -> 0 | AA43: 46164
A44: HB-4105095 | B44: 850707295238 | C44: ITM-700369 | D44: VF Corporation | E44: Vans | F44: Sk8-Hi | G44: VN000EBA57U | H44: Vans Sk8-Hi "Black/Black/White" Unisex Shoe | I44: Casual | J44: Canvas / Skate | K44: Unisex | L44: Black/Black/White | M44: 9 | N44: M - Medium | O44: SP26 | P44: Active | Q44: 84.99 | R44: 84.99 | S44: 42.89 | T44: 6 | V44: 2 | W44: 2 | X44: =SUM(T44:W44) -> 10 | Y44: =COUNT(T44:W44) -> 3 | Z44: =R44*X44 -> 849.9 | AA44: 46108
A45: HB-4103039 | B45: 803150555770 | C45: ITM-700243 | D45: New Balance Athletics, Inc. | E45: New Balance | F45: Fresh Foam X 1080v14 | G45: U3380ECV | H45: New Balance Fresh Foam X 1080v14 "Quartz Grey/Pink" Women's Shoe | I45: Running | J45: Premium Cushion | K45: Women | L45: Quartz Grey/Pink | M45: 6.5 | N45: B - Medium | O45: SU26 | P45: Active | Q45: 169.99 | R45: 169.99 | S45: 94.08 | T45: 1 | U45: 2 | V45: 4 | W45: 2 | X45: =SUM(T45:W45) -> 9 | Y45: =COUNT(T45:W45) -> 4 | Z45: =R45*X45 -> 1529.91 | AA45: 46166
A46: HB-4104927 | B46: 896414477909 | C46: ITM-700361 | D46: Converse, Inc. | E46: Converse | F46: Run Star Hike | G46: M9909B | H46: Converse Run Star Hike "Black/White/Gum" Women's Shoe | I46: Casual | J46: Canvas / Skate | K46: Women | L46: Black/White/Gum | M46: 6.5 | N46: B - Medium | O46: FA25 | P46: Clearance | Q46: 114.99 | R46: 85.99 | S46: 61.43 | T46: 0 | U46: 1 | V46: 2 | X46: =SUM(T46:W46) -> 3 | Y46: =COUNT(T46:W46) -> 3 | Z46: =R46*X46 -> 257.97 | AA46: 46057
A47: HB-4104671 | B47: 813642159654 | C47: ITM-700344 | D47: Saucony, Inc. | E47: Saucony | F47: Ride 18 | G47: S96470-35 | H47: Saucony Ride 18 "Shadow/Citron" Men's Shoe | I47: Running | J47: Neutral Cushion | K47: Men | L47: Shadow/Citron | M47: 10 | N47: D - Medium | O47: SP26 | P47: Clearance | Q47: 144.99 | R47: 93.99 | S47: 77.83 | T47: 2 | U47: 2 | V47: 0 | W47: 0 | X47: =SUM(T47:W47) -> 4 | Y47: =COUNT(T47:W47) -> 4 | Z47: =R47*X47 -> 375.96 | AA47: 46050
A48: HB-4103114 | B48: 845572583356 | C48: ITM-700247 | D48: New Balance Athletics, Inc. | E48: New Balance | F48: Fresh Foam Arishi v4 | G48: W8600KRG | H48: New Balance Fresh Foam Arishi v4 "Black/Silver" Men's Shoe | I48: Running | J48: Entry Cushion | K48: Men | L48: Black/Silver | M48: 12 | N48: D - Medium | O48: FA26 | P48: Active | Q48: 79.99 | R48: 79.99 | S48: 39.84 | T48: 2 | V48: 5 | X48: =SUM(T48:W48) -> 7 | Y48: =COUNT(T48:W48) -> 2 | Z48: =R48*X48 -> 559.93 | AA48: 46195
A49: HB-4101804 | B49: 835652288524 | C49: ITM-700187 | D49: adidas AG | E49: adidas Originals | F49: Samba OG | G49: SA8999 | H49: adidas Originals Samba OG "Core Black/White/Gum" Men's Shoe | I49: Casual | J49: Terrace / Lifestyle | K49: Men | L49: Core Black/White/Gum | M49: 8 | N49: D - Medium | O49: HO25 | P49: Clearance | Q49: 109.99 | R49: 65.99 | S49: 60.5 | T49: 3 | U49: 6 | V49: 7 | W49: 2 | X49: =SUM(T49:W49) -> 18 | Y49: =COUNT(T49:W49) -> 4 | Z49: =R49*X49 -> 1187.82 | AA49: 46180
A50: HB-4103420 | B50: 828321124030 | C50: ITM-700267 | D50: Under Armour, Inc. | E50: Under Armour | F50: Curry 12 | G50: 3029154-866 | H50: Under Armour Curry 12 "White/Team Royal" Men's Shoe | I50: Basketball | J50: Signature | K50: Men | L50: White/Team Royal | M50: 10.5 | N50: D - Medium | O50: SU26 | P50: Active | Q50: 169.99 | R50: 169.99 | S50: 86.49 | T50: 3 | U50: 3 | V50: 6 | X50: =SUM(T50:W50) -> 12 | Y50: =COUNT(T50:W50) -> 3 | Z50: =R50*X50 -> 2039.88 | AA50: 46115
A51: HB-4105572 | B51: 805051492756 | C51: ITM-700393 | D51: Fila | E51: Fila | F51: Disruptor II Premium | G51: 1FM67540-913 | H51: Fila Disruptor II Premium "White/Navy/Red" Women's Shoe | I51: Casual | J51: Chunky Lifestyle | K51: Women | L51: White/Navy/Red | M51: 7 | N51: B - Medium | O51: FA25 | P51: Clearance | Q51: 74.99 | R51: 51.99 | S51: 36.67 | V51: 3 | X51: =SUM(T51:W51) -> 3 | Y51: =COUNT(T51:W51) -> 1 | Z51: =R51*X51 -> 155.97 | AA51: 46199
A52: HB-4105407 | B52: 897157240809 | C52: ITM-700386 | D52: Crocs, Inc. | E52: Crocs | F52: Classic Clog | G52: 65263-575 | H52: Crocs Classic Clog "Black" Unisex Shoe | I52: Sandals | J52: Clogs | K52: Unisex | L52: Black | M52: 10 | N52: M - Medium | O52: SU26 | P52: Active | Q52: 54.99 | R52: 54.99 | S52: 29.66 | T52: 2 | U52: 0 | V52: 4 | W52: 3 | X52: =SUM(T52:W52) -> 9 | Y52: =COUNT(T52:W52) -> 4 | Z52: =R52*X52 -> 494.91 | AA52: 46099
A53: HB-4102340 | B53: 885756795239 | C53: ITM-700214 | D53: adidas AG | E53: adidas | F53: Ultraboost 5 | G53: BJ7996 | H53: adidas Ultraboost 5 "Core Black/Carbon" Men's Shoe | I53: Running | J53: Neutral Cushion | K53: Men | L53: Core Black/Carbon | M53: 10.5 | N53: D - Medium | O53: SU26 | P53: Active | Q53: 189.99 | R53: 189.99 | S53: 103.72 | T53: 2 | U53: 0 | V53: 0 | X53: =SUM(T53:W53) -> 2 | Y53: =COUNT(T53:W53) -> 3 | Z53: =R53*X53 -> 379.98 | AA53: 46183
A54: HB-4102608 | B54: 816959142013 | C54: ITM-700226 | D54: adidas AG | E54: adidas | F54: D.O.N. Issue 7 | G54: DJ5715 | H54: adidas D.O.N. Issue 7 "Black/Solar Red" Big Kids' Shoe | I54: Basketball | J54: Signature | K54: Big Kids | L54: Black/Solar Red | M54: 4.5Y | N54: M - Medium | O54: FA26 | P54: Pre-Season | Q54: 84.99 | R54: 84.99 | S54: 45.41 | V54: 3 | X54: =SUM(T54:W54) -> 3 | Y54: =COUNT(T54:W54) -> 1 | Z54: =R54*X54 -> 254.97 | AA54: 46049
A55: HB-4101216 | B55: 879216408133 | C55: ITM-700157 | D55: Nike, Inc. | E55: Nike | F55: Victori One Slide | G55: ZT3186-849 | H55: Nike Victori One Slide "Black/White" Men's Shoe | I55: Sandals | J55: Slides | K55: Men | L55: Black/White | M55: 8.5 | N55: D - Medium | O55: HO25 | P55: Clearance | Q55: 34.99 | R55: 23.99 | S55: 19 | T55: 2 | U55: 2 | V55: 3 | W55: 0 | X55: =SUM(T55:W55) -> 7 | Y55: =COUNT(T55:W55) -> 4 | Z55: =R55*X55 -> 167.93 | AA55: 46185
A56: HB-4102794 | B56: 861205482756 | C56: ITM-700230 | D56: New Balance Athletics, Inc. | E56: New Balance | F56: 9060 | G56: U1951JZR | H56: New Balance 9060 "Rain Cloud/Grey Matter" Men's Shoe | I56: Casual | J56: Retro Running | K56: Men | L56: Rain Cloud/Grey Matter | M56: 11.5 | N56: D - Medium | O56: HO25 | P56: Clearance | Q56: 149.99 | R56: 89.99 | S56: 74.84 | U56: 0 | V56: 6 | X56: =SUM(T56:W56) -> 6 | Y56: =COUNT(T56:W56) -> 2 | Z56: =R56*X56 -> 539.94 | AA56: 46205
A57: HB-4103132 | B57: 866971656165 | C57: ITM-700249 | D57: New Balance Athletics, Inc. | E57: New Balance | F57: FuelCell Propel v5 | G57: W8666FPC | H57: New Balance FuelCell Propel v5 "White/Vibrant Pink" Women's Shoe | I57: Running | J57: Tech Running | K57: Women | L57: White/Vibrant Pink | M57: 6 | N57: B - Medium | O57: HO25 | P57: Active | Q57: 139.99 | R57: 139.99 | S57: 78.24 | T57: 1 | U57: 5 | V57: 4 | W57: 4 | X57: =SUM(T57:W57) -> 14 | Y57: =COUNT(T57:W57) -> 4 | Z57: =R57*X57 -> 1959.86 | AA57: 46106
A58: HB-4102815 | B58: 828437016692 | C58: ITM-700232 | D58: New Balance Athletics, Inc. | E58: New Balance | F58: 530 | G58: U7401EJM | H58: New Balance 530 "White/Silver Navy" Women's Shoe | I58: Casual | J58: Retro Running | K58: Women | L58: White/Silver Navy | M58: 6.5 | N58: B - Medium | O58: SP26 | P58: Active | Q58: 99.99 | R58: 99.99 | S58: 53.26 | T58: 4 | U58: 4 | V58: 0 | W58: 2 | X58: =SUM(T58:W58) -> 10 | Y58: =COUNT(T58:W58) -> 4 | Z58: =R58*X58 -> 999.9 | AA58: 46029
A59: HB-4105298 | B59: 852902955069 | C59: ITM-700381 | D59: Skechers U.S.A., Inc. | E59: Skechers | F59: Go Walk 7 | G59: 232243-KJC | H59: Skechers Go Walk 7 "Black/Charcoal" Women's Shoe | I59: Running | J59: Walking | K59: Women | L59: Black/Charcoal | M59: 7.5 | N59: B - Medium | O59: SU26 | P59: Active | Q59: 79.99 | R59: 79.99 | S59: 41.06 | T59: 3 | U59: 3 | V59: 3 | X59: =SUM(T59:W59) -> 9 | Y59: =COUNT(T59:W59) -> 3 | Z59: =R59*X59 -> 719.91 | AA59: 46047
A60: HB-4100600 | B60: 818793307555 | C60: ITM-700126 | D60: Nike, Inc. | E60: Nike | F60: P-6000 | G60: VG1009-478 | H60: Nike P-6000 "Summit White/Metallic Silver" Women's Shoe | I60: Casual | J60: Retro Running | K60: Women | L60: Summit White/Metallic Silver | M60: 9 | N60: B - Medium | O60: FA26 | P60: Pre-Season | Q60: 119.99 | R60: 119.99 | S60: 62.97 | T60: 8 | V60: 0 | W60: 0 | X60: =SUM(T60:W60) -> 8 | Y60: =COUNT(T60:W60) -> 3 | Z60: =R60*X60 -> 959.92 | AA60: 46161
A61: HB-4103196 | B61: 860073277245 | C61: ITM-700252 | D61: Under Armour, Inc. | E61: Under Armour | F61: Charged Assert 10 | G61: 3028321-744 | H61: Under Armour Charged Assert 10 "Black/Black/White" Men's Shoe | I61: Running | J61: Entry Cushion | K61: Men | L61: Black/Black/White | M61: 9 | N61: D - Medium | O61: SP26 | P61: Clearance | Q61: 84.99 | R61: 54.99 | S61: 45.86 | T61: 2 | U61: 0 | V61: 0 | W61: 0 | X61: =SUM(T61:W61) -> 2 | Y61: =COUNT(T61:W61) -> 4 | Z61: =R61*X61 -> 109.98 | AA61: 46144
A62: HB-4101124 | B62: 887150863554 | C62: ITM-700155 | D62: Nike, Inc. | E62: Nike | F62: KD 17 | G62: SK9256-561 | H62: Nike KD 17 "Sail/University Red" Men's Shoe | I62: Basketball | J62: Signature | K62: Men | L62: Sail/University Red | M62: 9.5 | N62: D - Medium | O62: SU26 | P62: Active | Q62: 159.99 | R62: 159.99 | S62: 86.99 | T62: 1 | U62: 4 | V62: 6 | X62: =SUM(T62:W62) -> 11 | Y62: =COUNT(T62:W62) -> 3 | Z62: =R62*X62 -> 1759.89 | AA62: 46046
A63: HB-4101672 | B63: 858450938230 | C63: ITM-700181 | D63: Nike, Inc. | E63: Jordan | F63: Max Aura 6 | G63: VW8797-448 | H63: Jordan Max Aura 6 "Black/Anthracite/White" Men's Shoe | I63: Casual | J63: Court / Lifestyle | K63: Men | L63: Black/Anthracite/White | M63: 13 | N63: D - Medium | O63: FA25 | P63: Clearance | Q63: 109.99 | R63: 65.99 | S63: 57.5 | T63: 0 | U63: 1 | V63: 5 | W63: 0 | X63: =SUM(T63:W63) -> 6 | Y63: =COUNT(T63:W63) -> 4 | Z63: =R63*X63 -> 395.94 | AA63: 46056
A64: HB-4103966 | B64: 885110614087 | C64: ITM-700293 | D64: ASICS Corporation | E64: ASICS | F64: GEL-KAYANO 32 | G64: 1061B874-346 | H64: ASICS GEL-KAYANO 32 "Black/Graphite Grey" Men's Shoe | I64: Running | J64: Stability | K64: Men | L64: Black/Graphite Grey | M64: 9.5 | N64: D - Medium | O64: FA25 | P64: Clearance | Q64: 169.99 | R64: 101.99 | S64: 84.77 | V64: 3 | X64: =SUM(T64:W64) -> 3 | Y64: =COUNT(T64:W64) -> 1 | Z64: =R64*X64 -> 305.97 | AA64: 46210
A65: HB-4101303 | B65: 836791044856 | C65: ITM-700161 | D65: Nike, Inc. | E65: Jordan | F65: Air Jordan 1 Low | G65: RA8125-542 | H65: Jordan Air Jordan 1 Low "White/Black/Gym Red" Men's Shoe | I65: Casual | J65: Retro Basketball | K65: Men | L65: White/Black/Gym Red | M65: 12 | N65: D - Medium | O65: SP26 | P65: Active | Q65: 129.99 | R65: 129.99 | S65: 63.23 | T65: 2 | U65: 4 | V65: 7 | W65: 1 | X65: =SUM(T65:W65) -> 14 | Y65: =COUNT(T65:W65) -> 4 | Z65: =R65*X65 -> 1819.86 | AA65: 46173
A66: HB-4100738 | B66: 864256747963 | C66: ITM-700138 | D66: Nike, Inc. | E66: Nike | F66: Pegasus 41 | G66: MU0668-517 | H66: Nike Pegasus 41 "White/Pink Foam" Women's Shoe | I66: Running | J66: Neutral Cushion | K66: Women | L66: White/Pink Foam | M66: 6.5 | N66: B - Medium | O66: SU26 | P66: Active | Q66: 139.99 | R66: 139.99 | S66: 72.45 | T66: 5 | V66: 0 | X66: =SUM(T66:W66) -> 5 | Y66: =COUNT(T66:W66) -> 2 | Z66: =R66*X66 -> 699.95 | AA66: 46137
A67: HB-4102056 | B67: 818208630279 | C67: ITM-700197 | D67: adidas AG | E67: adidas Originals | F67: Campus 00s | G67: HF3277 | H67: adidas Originals Campus 00s "Dark Green/Off White" Men's Shoe | I67: Casual | J67: Terrace / Lifestyle | K67: Men | L67: Dark Green/Off White | M67: 12 | N67: D - Medium | O67: HO25 | P67: Clearance | Q67: 109.99 | R67: 76.99 | S67: 55.09 | T67: 2 | U67: 2 | V67: 2 | W67: 0 | X67: =SUM(T67:W67) -> 6 | Y67: =COUNT(T67:W67) -> 4 | Z67: =R67*X67 -> 461.94 | AA67: 46202
A68: HB-4103288 | B68: 883361532207 | C68: ITM-700256 | D68: Under Armour, Inc. | E68: Under Armour | F68: Charged Rogue 4 | G68: 3021829-818 | H68: Under Armour Charged Rogue 4 "Grey/Black" Men's Shoe | I68: Running | J68: Neutral Cushion | K68: Men | L68: Grey/Black | M68: 10 | N68: D - Medium | O68: SU26 | P68: Active | Q68: 99.99 | R68: 99.99 | S68: 51.72 | T68: 3 | U68: 3 | W68: 2 | X68: =SUM(T68:W68) -> 8 | Y68: =COUNT(T68:W68) -> 3 | Z68: =R68*X68 -> 799.92 | AA68: 46041
A69: HB-4101397 | B69: 852715238748 | C69: ITM-700167 | D69: Nike, Inc. | E69: Jordan | F69: Air Jordan 1 Mid | G69: XA0640-217 | H69: Jordan Air Jordan 1 Mid "Black/White/Gym Red" Big Kids' Shoe | I69: Casual | J69: Retro Basketball | K69: Big Kids | L69: Black/White/Gym Red | M69: 4.5Y | N69: M - Medium | O69: SU26 | P69: Active | Q69: 114.99 | R69: 114.99 | S69: 56.56 | U69: 6 | V69: 6 | X69: =SUM(T69:W69) -> 12 | Y69: =COUNT(T69:W69) -> 2 | Z69: =R69*X69 -> 1379.88 | AA69: 46189
A70: HB-4100528 | B70: 889476146039 | C70: ITM-700122 | D70: Nike, Inc. | E70: Nike | F70: Court Vision Low Next Nature | G70: CC5588-537 | H70: Nike Court Vision Low Next Nature "White/Black" Men's Shoe | I70: Casual | J70: Court / Lifestyle | K70: Men | L70: White/Black | M70: 9 | N70: D - Medium | O70: SU26 | P70: Active | Q70: 79.99 | R70: 79.99 | S70: 42.84 | T70: 1 | U70: 0 | V70: 3 | W70: 2 | X70: =SUM(T70:W70) -> 6 | Y70: =COUNT(T70:W70) -> 4 | Z70: =R70*X70 -> 479.94 | AA70: 46186
A71: HB-4101145 | B71: 858120599031 | C71: ITM-700155 | D71: Nike, Inc. | E71: Nike | F71: KD 17 | G71: SK9256-561 | H71: Nike KD 17 "Sail/University Red" Men's Shoe | I71: Basketball | J71: Signature | K71: Men | L71: Sail/University Red | M71: 10.5 | N71: D - Medium | O71: SU26 | P71: Active | Q71: 159.99 | R71: 159.99 | S71: 86.99 | T71: 3 | U71: 4 | V71: 5 | X71: =SUM(T71:W71) -> 12 | Y71: =COUNT(T71:W71) -> 3 | Z71: =R71*X71 -> 1919.88 | AA71: 46036
A72: HB-4101252 | B72: 880091896698 | C72: ITM-700160 | D72: Nike, Inc. | E72: Nike | F72: Kawa Slide | G72: XR1080-146 | H72: Nike Kawa Slide "Black/White" Little Kids' Shoe | I72: Sandals | J72: Slides | K72: Little Kids | L72: Black/White | M72: 12C | N72: M - Medium | O72: FA26 | P72: Active | Q72: 27.99 | R72: 27.99 | S72: 14.09 | T72: 4 | V72: 7 | X72: =SUM(T72:W72) -> 11 | Y72: =COUNT(T72:W72) -> 2 | Z72: =R72*X72 -> 307.89 | AA72: 46134
A73: HB-4100688 | B73: 835175562927 | C73: ITM-700134 | D73: Nike, Inc. | E73: Nike | F73: Pegasus 41 | G73: BA2983-804 | H73: Nike Pegasus 41 "Black/White/Volt" Men's Shoe | I73: Running | J73: Neutral Cushion | K73: Men | L73: Black/White/Volt | M73: 9.5 | N73: D - Medium | O73: FA26 | P73: Active | Q73: 139.99 | R73: 139.99 | S73: 75.33 | V73: 5 | W73: 2 | X73: =SUM(T73:W73) -> 7 | Y73: =COUNT(T73:W73) -> 2 | Z73: =R73*X73 -> 979.93 | AA73: 46215
A74: HB-4104243 | B74: 801795343370 | C74: ITM-700310 | D74: Brooks Sports, Inc. | E74: Brooks | F74: Ghost 17 | G74: 110343-1D-175 | H74: Brooks Ghost 17 "White/Coral/Peach" Women's Shoe | I74: Running | J74: Neutral Cushion | K74: Women | L74: White/Coral/Peach | M74: 10 | N74: B - Medium | O74: FA26 | P74: Pre-Season | Q74: 149.99 | R74: 149.99 | S74: 73.89 | U74: 5 | V74: 0 | W74: 5 | X74: =SUM(T74:W74) -> 10 | Y74: =COUNT(T74:W74) -> 3 | Z74: =R74*X74 -> 1499.9 | AA74: 46159
A75: HB-4100235 | B75: 869658153031 | C75: ITM-700115 | D75: Nike, Inc. | E75: Nike | F75: Air Max 95 | G75: ZK9121-255 | H75: Nike Air Max 95 "Neutral Grey/Black/Volt" Men's Shoe | I75: Casual | J75: Retro Running | K75: Men | L75: Neutral Grey/Black/Volt | M75: 10 | N75: D - Medium | O75: SP26 | P75: Active | Q75: 189.99 | R75: 189.99 | S75: 101.4 | T75: 3 | V75: 8 | X75: =SUM(T75:W75) -> 11 | Y75: =COUNT(T75:W75) -> 2 | Z75: =R75*X75 -> 2089.89 | AA75: 46092
A76: HB-4101542 | B76: 894087863806 | C76: ITM-700177 | D76: Nike, Inc. | E76: Jordan | F76: Air Jordan 13 Retro | G76: YD8499-570 | H76: Jordan Air Jordan 13 Retro "Black/Gym Red" Big Kids' Shoe | I76: Casual | J76: Retro Basketball | K76: Big Kids | L76: Black/Gym Red | M76: 5.5Y | N76: M - Medium | O76: FA26 | P76: Active | Q76: 154.99 | R76: 154.99 | S76: 85.71 | T76: 6 | V76: 5 | W76: 4 | X76: =SUM(T76:W76) -> 15 | Y76: =COUNT(T76:W76) -> 3 | Z76: =R76*X76 -> 2324.85 | AA76: 46109
A77: HB-4100699 | B77: 889560976690 | C77: ITM-700134 | D77: Nike, Inc. | E77: Nike | F77: Pegasus 41 | G77: BA2983-804 | H77: Nike Pegasus 41 "Black/White/Volt" Men's Shoe | I77: Running | J77: Neutral Cushion | K77: Men | L77: Black/White/Volt | M77: 10.5 | N77: D - Medium | O77: FA26 | P77: Active | Q77: 139.99 | R77: 139.99 | S77: 75.33 | V77: 4 | W77: 0 | X77: =SUM(T77:W77) -> 4 | Y77: =COUNT(T77:W77) -> 2 | Z77: =R77*X77 -> 559.96 | AA77: 46176
A78: HB-4101979 | B78: 882834255843 | C78: ITM-700190 | D78: adidas AG | E78: adidas Originals | F78: Gazelle | G78: UB7109 | H78: adidas Originals Gazelle "Collegiate Navy/White" Women's Shoe | I78: Casual | J78: Terrace / Lifestyle | K78: Women | L78: Collegiate Navy/White | M78: 8 | N78: B - Medium | O78: FA25 | P78: Active | Q78: 99.99 | R78: 99.99 | S78: 54.14 | T78: 2 | U78: 4 | V78: 4 | W78: 1 | X78: =SUM(T78:W78) -> 11 | Y78: =COUNT(T78:W78) -> 4 | Z78: =R78*X78 -> 1099.89 | AA78: 46133
A79: HB-4102381 | B79: 870010516569 | C79: ITM-700214 | D79: adidas AG | E79: adidas | F79: Ultraboost 5 | G79: BJ7996 | H79: adidas Ultraboost 5 "Core Black/Carbon" Men's Shoe | I79: Running | J79: Neutral Cushion | K79: Men | L79: Core Black/Carbon | M79: 12 | N79: D - Medium | O79: SU26 | P79: Active | Q79: 189.99 | R79: 189.99 | S79: 103.72 | T79: 0 | U79: 2 | V79: 3 | X79: =SUM(T79:W79) -> 5 | Y79: =COUNT(T79:W79) -> 3 | Z79: =R79*X79 -> 949.95 | AA79: 46067
A80: HB-4100816 | B80: 834770416370 | C80: ITM-700144 | D80: Nike, Inc. | E80: Nike | F80: Revolution 7 | G80: PA7227-732 | H80: Nike Revolution 7 "White/Aquarius Blue" Big Kids' Shoe | I80: Running | J80: Entry Cushion | K80: Big Kids | L80: White/Aquarius Blue | M80: 5.5Y | N80: M - Medium | O80: SU26 | P80: Active | Q80: 59.99 | R80: 59.99 | S80: 29.23 | T80: 1 | U80: 0 | V80: 4 | W80: 0 | X80: =SUM(T80:W80) -> 5 | Y80: =COUNT(T80:W80) -> 4 | Z80: =R80*X80 -> 299.95 | AA80: 46112
A81: HB-4101467 | B81: 820776221945 | C81: ITM-700171 | D81: Nike, Inc. | E81: Jordan | F81: Air Jordan 4 Retro | G81: DE6531-963 | H81: Jordan Air Jordan 4 Retro "White/Black/Neutral Grey" Men's Shoe | I81: Casual | J81: Retro Basketball | K81: Men | L81: White/Black/Neutral Grey | M81: 9 | N81: D - Medium | O81: SP26 | P81: Active | Q81: 224.99 | R81: 224.99 | S81: 120.83 | T81: 0 | U81: 1 | V81: 3 | X81: =SUM(T81:W81) -> 4 | Y81: =COUNT(T81:W81) -> 3 | Z81: =R81*X81 -> 899.96 | AA81: 46074
A82: HB-4103551 | B82: 873898885332 | C82: ITM-700274 | D82: PUMA SE | E82: PUMA | F82: Suede Classic XXI | G82: 945672-51 | H82: PUMA Suede Classic XXI "Black/White" Men's Shoe | I82: Casual | J82: Court / Lifestyle | K82: Men | L82: Black/White | M82: 10 | N82: D - Medium | O82: FA26 | P82: Active | Q82: 79.99 | R82: 79.99 | S82: 44.53 | T82: 1 | U82: 1 | V82: 5 | W82: 0 | X82: =SUM(T82:W82) -> 7 | Y82: =COUNT(T82:W82) -> 4 | Z82: =R82*X82 -> 559.93 | AA82: 46054
A83: HB-4101685 | B83: 848985487899 | C83: ITM-700182 | D83: Nike, Inc. | E83: Jordan | F83: Tatum 3 | G83: GH5159-500 | H83: Jordan Tatum 3 "Wolf Grey/Celtic Green" Men's Shoe | I83: Basketball | J83: Signature | K83: Men | L83: Wolf Grey/Celtic Green | M83: 11.5 | N83: D - Medium | O83: SU26 | P83: Active | Q83: 119.99 | R83: 119.99 | S83: 62.47 | V83: 4 | X83: =SUM(T83:W83) -> 4 | Y83: =COUNT(T83:W83) -> 1 | Z83: =R83*X83 -> 479.96 | AA83: 46145
A84: HB-4102838 | B84: 856742417830 | C84: ITM-700232 | D84: New Balance Athletics, Inc. | E84: New Balance | F84: 530 | G84: U7401EJM | H84: New Balance 530 "White/Silver Navy" Women's Shoe | I84: Casual | J84: Retro Running | K84: Women | L84: White/Silver Navy | M84: 7.5 | N84: B - Medium | O84: SP26 | P84: Active | Q84: 99.99 | R84: 99.99 | S84: 53.26 | T84: 6 | U84: 1 | V84: 0 | W84: 0 | X84: =SUM(T84:W84) -> 7 | Y84: =COUNT(T84:W84) -> 4 | Z84: =R84*X84 -> 699.93 | AA84: 46042
A85: HB-4101716 | B85: 858905656200 | C85: ITM-700182 | D85: Nike, Inc. | E85: Jordan | F85: Tatum 3 | G85: GH5159-500 | H85: Jordan Tatum 3 "Wolf Grey/Celtic Green" Men's Shoe | I85: Basketball | J85: Signature | K85: Men | L85: Wolf Grey/Celtic Green | M85: 13 | N85: D - Medium | O85: SU26 | P85: Active | Q85: 119.99 | R85: 119.99 | S85: 62.47 | V85: 4 | X85: =SUM(T85:W85) -> 4 | Y85: =COUNT(T85:W85) -> 1 | Z85: =R85*X85 -> 479.96 | AA85: 46066
A86: HB-4104832 | B86: 862118891387 | C86: ITM-700352 | D86: Converse, Inc. | E86: Converse | F86: Chuck Taylor All Star Low | G86: A4852J | H86: Converse Chuck Taylor All Star Low "Optical White" Unisex Shoe | I86: Casual | J86: Canvas / Skate | K86: Unisex | L86: Optical White | M86: 10 | N86: M - Medium | O86: SP26 | P86: Active | Q86: 64.99 | R86: 64.99 | S86: 34.43 | V86: 5 | X86: =SUM(T86:W86) -> 5 | Y86: =COUNT(T86:W86) -> 1 | Z86: =R86*X86 -> 324.95 | AA86: 46098
A87: HB-4102721 | B87: 811788883752 | C87: ITM-700228 | D87: New Balance Athletics, Inc. | E87: New Balance | F87: 574 Core | G87: M3056NPK | H87: New Balance 574 Core "Navy/White" Women's Shoe | I87: Casual | J87: Retro Running | K87: Women | L87: Navy/White | M87: 7 | N87: B - Medium | O87: FA25 | P87: Active | Q87: 89.99 | R87: 89.99 | S87: 44 | T87: 4 | U87: 2 | V87: 6 | X87: =SUM(T87:W87) -> 12 | Y87: =COUNT(T87:W87) -> 3 | Z87: =R87*X87 -> 1079.88 | AA87: 46031
A88: HB-4105680 | B88: 846738361021 | C88: ITM-700398 | D88: Deckers Brands | E88: UGG | F88: Tasman Slipper | G88: 1488404-UPU | H88: UGG Tasman Slipper "Chestnut" Women's Shoe | I88: Casual | J88: Slippers | K88: Women | L88: Chestnut | M88: 8 | N88: B - Medium | O88: HO25 | P88: Clearance | Q88: 119.99 | R88: 71.99 | S88: 61.14 | T88: 5 | U88: 6 | V88: 5 | W88: 0 | X88: =SUM(T88:W88) -> 16 | Y88: =COUNT(T88:W88) -> 4 | Z88: =R88*X88 -> 1151.84 | AA88: 46223
A89: HB-4102479 | B89: 896113860031 | C89: ITM-700221 | D89: adidas AG | E89: adidas | F89: Runfalcon 5 | G89: VY1130 | H89: adidas Runfalcon 5 "Core Black/White" Big Kids' Shoe | I89: Running | J89: Entry Cushion | K89: Big Kids | L89: Core Black/White | M89: 5.5Y | N89: M - Medium | O89: SU26 | P89: Active | Q89: 54.99 | R89: 54.99 | S89: 28.09 | T89: 1 | V89: 7 | X89: =SUM(T89:W89) -> 8 | Y89: =COUNT(T89:W89) -> 2 | Z89: =R89*X89 -> 439.92 | AA89: 46157
A90: HB-4103575 | B90: 876545250579 | C90: ITM-700274 | D90: PUMA SE | E90: PUMA | F90: Suede Classic XXI | G90: 945672-51 | H90: PUMA Suede Classic XXI "Black/White" Men's Shoe | I90: Casual | J90: Court / Lifestyle | K90: Men | L90: Black/White | M90: 11 | N90: D - Medium | O90: FA26 | P90: Active | Q90: 79.99 | R90: 79.99 | S90: 44.53 | T90: 0 | U90: 4 | V90: 5 | W90: 1 | X90: =SUM(T90:W90) -> 10 | Y90: =COUNT(T90:W90) -> 4 | Z90: =R90*X90 -> 799.9 | AA90: 46126
A91: HB-4102194 | B91: 852071747342 | C91: ITM-700203 | D91: adidas AG | E91: adidas Originals | F91: Forum Low | G91: WH3343 | H91: adidas Originals Forum Low "White/Collegiate Royal" Men's Shoe | I91: Casual | J91: Court / Lifestyle | K91: Men | L91: White/Collegiate Royal | M91: 13 | N91: D - Medium | O91: SU26 | P91: Active | Q91: 109.99 | R91: 109.99 | S91: 59.52 | T91: 4 | U91: 4 | V91: 1 | X91: =SUM(T91:W91) -> 9 | Y91: =COUNT(T91:W91) -> 3 | Z91: =R91*X91 -> 989.91 | AA91: 46054
A92: HB-4100059 | B92: 853848722842 | C92: ITM-700106 | D92: Nike, Inc. | E92: Nike | F92: Air Force 1 '07 | G92: WW7998-474 | H92: Nike Air Force 1 '07 "White/Black" Women's Shoe | I92: Casual | J92: Court / Lifestyle | K92: Women | L92: White/Black | M92: 6.5 | N92: B - Medium | O92: FA26 | P92: Active | Q92: 124.99 | R92: 124.99 | S92: 66.91 | T92: 0 | U92: 1 | V92: 5 | W92: 2 | X92: =SUM(T92:W92) -> 8 | Y92: =COUNT(T92:W92) -> 4 | Z92: =R92*X92 -> 999.92 | AA92: 46123
A93: HB-4101826 | B93: 872827662527 | C93: ITM-700187 | D93: adidas AG | E93: adidas Originals | F93: Samba OG | G93: SA8999 | H93: adidas Originals Samba OG "Core Black/White/Gum" Men's Shoe | I93: Casual | J93: Terrace / Lifestyle | K93: Men | L93: Core Black/White/Gum | M93: 9 | N93: D - Medium | O93: HO25 | P93: Clearance | Q93: 109.99 | R93: 65.99 | S93: 60.5 | T93: 3 | U93: 1 | V93: 0 | W93: 4 | X93: =SUM(T93:W93) -> 8 | Y93: =COUNT(T93:W93) -> 4 | Z93: =R93*X93 -> 527.92 | AA93: 46074
A94: HB-4102128 | B94: 865700186006 | C94: ITM-700200 | D94: adidas AG | E94: adidas Originals | F94: Superstar | G94: UP8227 | H94: adidas Originals Superstar "White/Core Black" Big Kids' Shoe | I94: Casual | J94: Court / Lifestyle | K94: Big Kids | L94: White/Core Black | M94: 6Y | N94: M - Medium | O94: FA26 | P94: Active | Q94: 74.99 | R94: 74.99 | S94: 39.21 | T94: 3 | U94: 4 | V94: 4 | W94: 1 | X94: =SUM(T94:W94) -> 12 | Y94: =COUNT(T94:W94) -> 4 | Z94: =R94*X94 -> 899.88 | AA94: 46022
A95: HB-4102636 | B95: 876100174156 | C95: ITM-700226 | D95: adidas AG | E95: adidas | F95: D.O.N. Issue 7 | G95: DJ5715 | H95: adidas D.O.N. Issue 7 "Black/Solar Red" Big Kids' Shoe | I95: Basketball | J95: Signature | K95: Big Kids | L95: Black/Solar Red | M95: 5.5Y | N95: M - Medium | O95: FA26 | P95: Pre-Season | Q95: 84.99 | R95: 84.99 | S95: 45.41 | V95: 2 | X95: =SUM(T95:W95) -> 2 | Y95: =COUNT(T95:W95) -> 1 | Z95: =R95*X95 -> 169.98 | AA95: 46111
A96: HB-4105078 | B96: 808494171404 | C96: ITM-700369 | D96: VF Corporation | E96: Vans | F96: Sk8-Hi | G96: VN000EBA57U | H96: Vans Sk8-Hi "Black/Black/White" Unisex Shoe | I96: Casual | J96: Canvas / Skate | K96: Unisex | L96: Black/Black/White | M96: 7 | N96: M - Medium | O96: SP26 | P96: Active | Q96: 84.99 | R96: 84.99 | S96: 42.89 | T96: 0 | V96: 7 | W96: 3 | X96: =SUM(T96:W96) -> 10 | Y96: =COUNT(T96:W96) -> 3 | Z96: =R96*X96 -> 849.9 | AA96: 46119
A97: HB-4105351 | B97: 840418736161 | C97: ITM-700385 | D97: Skechers U.S.A., Inc. | E97: Skechers | F97: Arch Fit 2.0 | G97: 215286-HPF | H97: Skechers Arch Fit 2.0 "Grey/Navy" Men's Shoe | I97: Running | J97: Walking | K97: Men | L97: Grey/Navy | M97: 9.5 | N97: D - Medium | O97: SU26 | P97: Active | Q97: 99.99 | R97: 99.99 | S97: 55.37 | T97: 1 | V97: 3 | W97: 4 | X97: =SUM(T97:W97) -> 8 | Y97: =COUNT(T97:W97) -> 3 | Z97: =R97*X97 -> 799.92 | AA97: 46166
A98: HB-4103672 | B98: 849533601537 | C98: ITM-700279 | D98: PUMA SE | E98: PUMA | F98: Speedcat OG | G98: 301419-53 | H98: PUMA Speedcat OG "Black/White" Women's Shoe | I98: Casual | J98: Motorsport / Lifestyle | K98: Women | L98: Black/White | M98: 6 | N98: B - Medium | O98: SP26 | P98: Active | Q98: 99.99 | R98: 99.99 | S98: 53.97 | T98: 2 | V98: 6 | X98: =SUM(T98:W98) -> 8 | Y98: =COUNT(T98:W98) -> 2 | Z98: =R98*X98 -> 799.92 | AA98: 46142
A99: HB-4101141 | B99: 865817320290 | C99: ITM-700155 | D99: Nike, Inc. | E99: Nike | F99: KD 17 | G99: SK9256-561 | H99: Nike KD 17 "Sail/University Red" Men's Shoe | I99: Basketball | J99: Signature | K99: Men | L99: Sail/University Red | M99: 10 | N99: D - Medium | O99: SU26 | P99: Active | Q99: 159.99 | R99: 159.99 | S99: 86.99 | T99: 4 | U99: 3 | V99: 2 | X99: =SUM(T99:W99) -> 9 | Y99: =COUNT(T99:W99) -> 3 | Z99: =R99*X99 -> 1439.91 | AA99: 46137
A100: HB-4105254 | B100: 863887477131 | C100: ITM-700377 | D100: Reebok International Ltd. | E100: Reebok | F100: Nano X5 | G100: 100026264 | H100: Reebok Nano X5 "Black/Grey/Yellow" Men's Shoe | I100: Training | J100: Cross Training | K100: Men | L100: Black/Grey/Yellow | M100: 8 | N100: D - Medium | O100: SP26 | P100: Active | Q100: 149.99 | R100: 149.99 | S100: 72.27 | V100: 5 | X100: =SUM(T100:W100) -> 5 | Y100: =COUNT(T100:W100) -> 1 | Z100: =R100*X100 -> 749.95 | AA100: 46176
...

Sheet Backroom Shelving 0146
A1: SKU | B1: UPC | C1: Item ID | D1: Brand | E1: Model | F1: Product Description | G1: Size | H1: On Hand - Store 0146 | I1: Sales Floor Units | J1: Back Room Units | K1: Stock Status | L1: Zone | M1: Zone Description | N1: Bay | O1: Shelf Level | P1: Bin | Q1: Location ID | R1: Shelf Label | S1: Shelf Height / Reach | T1: Overstock Location | U1: Pick Sequence | V1: Last Counted | W1: Suggested Agent Response
A2: HB-4104042 | B2: 818474894825 | C2: ITM-700298 | D2: ASICS | E2: GEL-EXCITE 11 | F2: ASICS GEL-EXCITE 11 "Black/Carrier Grey" Men's Shoe | G2: 9.5 | H2: =IFERROR(INDEX('Inventory Master'!$T$2:$T$525,MATCH($A2,'Inventory Master'!$A$2:$A$525,0)),0) -> 5 | I2: 0 | J2: =MAX(0,$H2-$I2) -> 5 | K2: =IF($H2>0,"In Stock","Out of Stock") -> In Stock | L2: A | M2: Men's Running & Training | N2: 1 | O2: 1 | P2: 1 | Q2: =$L2&"-"&TEXT($N2,"00")&"-"&$O2&"-"&TEXT($P2,"00") -> A-01-1-01 | R2: ="ZONE "&$L2&" / BAY "&TEXT($N2,"00")&" / SHELF "&$O2&" / BIN "&TEXT($P2,"00") -> ZONE A / BAY 01 / SHELF 1 / BIN 01 | S2: Floor level - no reach | T2: n/a | U2: 1 | V2: 46145 | W2: =IF($H2>0,"Yes - "&$H2&" in stock at Store 0146 (size "&$G2&"). Back room location "&$Q2&" ("&$R2&"), "&$S2&". Back room "&$J2&" / sales floor "&$I2&".","Not currently in stock at Store 0146 (size "&$G2&"). Home location is "&$Q2&" ("&$R2&") when replenished.") -> Yes - 5 in stock at Store 0146 (size 9.5). Back room location A-01-1-01 (ZONE A / BAY 01 / SHELF 1 / BIN 01), Floor level - no reach. Back room 5 / sales floor 0.
A3: HB-4104054 | B3: 855904345660 | C3: ITM-700298 | D3: ASICS | E3: GEL-EXCITE 11 | F3: ASICS GEL-EXCITE 11 "Black/Carrier Grey" Men's Shoe | G3: 10 | H3: =IFERROR(INDEX('Inventory Master'!$T$2:$T$525,MATCH($A3,'Inventory Master'!$A$2:$A$525,0)),0) -> 3 | I3: 2 | J3: =MAX(0,$H3-$I3) -> 1 | K3: =IF($H3>0,"In Stock","Out of Stock") -> In Stock | L3: A | M3: Men's Running & Training | N3: 1 | O3: 1 | P3: 2 | Q3: =$L3&"-"&TEXT($N3,"00")&"-"&$O3&"-"&TEXT($P3,"00") -> A-01-1-02 | R3: ="ZONE "&$L3&" / BAY "&TEXT($N3,"00")&" / SHELF "&$O3&" / BIN "&TEXT($P3,"00") -> ZONE A / BAY 01 / SHELF 1 / BIN 02 | S3: Floor level - no reach | T3: n/a | U3: 2 | V3: 46179 | W3: =IF($H3>0,"Yes - "&$H3&" in stock at Store 0146 (size "&$G3&"). Back room location "&$Q3&" ("&$R3&"), "&$S3&". Back room "&$J3&" / sales floor "&$I3&".","Not currently in stock at Store 0146 (size "&$G3&"). Home location is "&$Q3&" ("&$R3&") when replenished.") -> Yes - 3 in stock at Store 0146 (size 10). Back room location A-01-1-02 (ZONE A / BAY 01 / SHELF 1 / BIN 02), Floor level - no reach. Back room 1 / sales floor 2.
A4: HB-4104069 | B4: 811895179780 | C4: ITM-700298 | D4: ASICS | E4: GEL-EXCITE 11 | F4: ASICS GEL-EXCITE 11 "Black/Carrier Grey" Men's Shoe | G4: 10.5 | H4: =IFERROR(INDEX('Inventory Master'!$T$2:$T$525,MATCH($A4,'Inventory Master'!$A$2:$A$525,0)),0) -> 0 | I4: 0 | J4: =MAX(0,$H4-$I4) -> 0 | K4: =IF($H4>0,"In Stock","Out of Stock") -> Out of Stock | L4: A | M4: Men's Running & Training | N4: 1 | O4: 1 | P4: 3 | Q4: =$L4&"-"&TEXT($N4,"00")&"-"&$O4&"-"&TEXT($P4,"00") -> A-01-1-03 | R4: ="ZONE "&$L4&" / BAY "&TEXT($N4,"00")&" / SHELF "&$O4&" / BIN "&TEXT($P4,"00") -> ZONE A / BAY 01 / SHELF 1 / BIN 03 | S4: Floor level - no reach | T4: n/a | U4: 3 | V4: 46160 | W4: =IF($H4>0,"Yes - "&$H4&" in stock at Store 0146 (size "&$G4&"). Back room location "&$Q4&" ("&$R4&"), "&$S4&". Back room "&$J4&" / sales floor "&$I4&".","Not currently in stock at Store 0146 (size "&$G4&"). Home location is "&$Q4&" ("&$R4&") when replenished.") -> Not currently in stock at Store 0146 (size 10.5). Home location is A-01-1-03 (ZONE A / BAY 01 / SHELF 1 / BIN 03) when replenished.
A5: HB-4104088 | B5: 848629257426 | C5: ITM-700298 | D5: ASICS | E5: GEL-EXCITE 11 | F5: ASICS GEL-EXCITE 11 "Black/Carrier Grey" Men's Shoe | G5: 11 | H5: =IFERROR(INDEX('Inventory Master'!$T$2:$T$525,MATCH($A5,'Inventory Master'!$A$2:$A$525,0)),0) -> 2 | I5: 0 | J5: =MAX(0,$H5-$I5) -> 2 | K5: =IF($H5>0,"In Stock","Out of Stock") -> In Stock | L5: A | M5: Men's Running & Training | N5: 1 | O5: 1 | P5: 4 | Q5: =$L5&"-"&TEXT($N5,"00")&"-"&$O5&"-"&TEXT($P5,"00") -> A-01-1-04 | R5: ="ZONE "&$L5&" / BAY "&TEXT($N5,"00")&" / SHELF "&$O5&" / BIN "&TEXT($P5,"00") -> ZONE A / BAY 01 / SHELF 1 / BIN 04 | S5: Floor level - no reach | T5: n/a | U5: 4 | V5: 46221 | W5: =IF($H5>0,"Yes - "&$H5&" in stock at Store 0146 (size "&$G5&"). Back room location "&$Q5&" ("&$R5&"), "&$S5&". Back room "&$J5&" / sales floor "&$I5&".","Not currently in stock at Store 0146 (size "&$G5&"). Home location is "&$Q5&" ("&$R5&") when replenished.") -> Yes - 2 in stock at Store 0146 (size 11). Back room location A-01-1-04 (ZONE A / BAY 01 / SHELF 1 / BIN 04), Floor level - no reach. Back room 2 / sales floor 0.
A6: HB-4104096 | B6: 882194120494 | C6: ITM-700298 | D6: ASICS | E6: GEL-EXCITE 11 | F6: ASICS GEL-EXCITE 11 "Black/Carrier Grey" Men's Shoe | G6: 11.5 | H6: =IFERROR(INDEX('Inventory Master'!$T$2:$T$525,MATCH($A6,'Inventory Master'!$A$2:$A$525,0)),0) -> 0 | I6: 0 | J6: =MAX(0,$H6-$I6) -> 0 | K6: =IF($H6>0,"In Stock","Out of Stock") -> Out of Stock | L6: A | M6: Men's Running & Training | N6: 1 | O6: 1 | P6: 5 | Q6: =$L6&"-"&TEXT($N6,"00")&"-"&$O6&"-"&TEXT($P6,"00") -> A-01-1-05 | R6: ="ZONE "&$L6&" / BAY "&TEXT($N6,"00")&" / SHELF "&$O6&" / BIN "&TEXT($P6,"00") -> ZONE A / BAY 01 / SHELF 1 / BIN 05 | S6: Floor level - no reach | T6: n/a | U6: 5 | V6: 46176 | W6: =IF($H6>0,"Yes - "&$H6&" in stock at Store 0146 (size "&$G6&"). Back room location "&$Q6&" ("&$R6&"), "&$S6&". Back room "&$J6&" / sales floor "&$I6&".","Not currently in stock at Store 0146 (size "&$G6&"). Home location is "&$Q6&" ("&$R6&") when replenished.") -> Not currently in stock at Store 0146 (size 11.5). Home location is A-01-1-05 (ZONE A / BAY 01 / SHELF 1 / BIN 05) when replenished.
A7: HB-4104203 | B7: 876458462134 | C7: ITM-700306 | D7: Brooks | E7: Ghost 17 | F7: Brooks Ghost 17 "Black/Ebony/Grey" Men's Shoe | G7: 8 | H7: =IFERROR(INDEX('Inventory Master'!$T$2:$T$525,MATCH($A7,'Inventory Master'!$A$2:$A$525,0)),0) -> 1 | I7: 1 | J7: =MAX(0,$H7-$I7) -> 0 | K7: =IF($H7>0,"In Stock","Out of Stock") -> In Stock | L7: A | M7: Men's Running & Training | N7: 1 | O7: 2 | P7: 1 | Q7: =$L7&"-"&TEXT($N7,"00")&"-"&$O7&"-"&TEXT($P7,"00") -> A-01-2-01 | R7: ="ZONE "&$L7&" / BAY "&TEXT($N7,"00")&" / SHELF "&$O7&" / BIN "&TEXT($P7,"00") -> ZONE A / BAY 01 / SHELF 2 / BIN 01 | S7: Waist height | T7: n/a | U7: 6 | V7: 46141 | W7: =IF($H7>0,"Yes - "&$H7&" in stock at Store 0146 (size "&$G7&"). Back room location "&$Q7&" ("&$R7&"), "&$S7&". Back room "&$J7&" / sales floor "&$I7&".","Not currently in stock at Store 0146 (size "&$G7&"). Home location is "&$Q7&" ("&$R7&") when replenished.") -> Yes - 1 in stock at Store 0146 (size 8). Back room location A-01-2-01 (ZONE A / BAY 01 / SHELF 2 / BIN 01), Waist height. Back room 0 / sales floor 1.
A8: HB-4104206 | B8: 859477541235 | C8: ITM-700306 | D8: Brooks | E8: Ghost 17 | F8: Brooks Ghost 17 "Black/Ebony/Grey" Men's Shoe | G8: 8.5 | H8: =IFERROR(INDEX('Inventory Master'!$T$2:$T$525,MATCH($A8,'Inventory Master'!$A$2:$A$525,0)),0) -> 4 | I8: 2 | J8: =MAX(0,$H8-$I8) -> 2 | K8: =IF($H8>0,"In Stock","Out of Stock") -> In Stock | L8: A | M8: Men's Running & Training | N8: 1 | O8: 2 | P8: 2 | Q8: =$L8&"-"&TEXT($N8,"00")&"-"&$O8&"-"&TEXT($P8,"00") -> A-01-2-02 | R8: ="ZONE "&$L8&" / BAY "&TEXT($N8,"00")&" / SHELF "&$O8&" / BIN "&TEXT($P8,"00") -> ZONE A / BAY 01 / SHELF 2 / BIN 02 | S8: Waist height | T8: n/a | U8: 7 | V8: 46198 | W8: =IF($H8>0,"Yes - "&$H8&" in stock at Store 0146 (size "&$G8&"). Back room location "&$Q8&" ("&$R8&"), "&$S8&". Back room "&$J8&" / sales floor "&$I8&".","Not currently in stock at Store 0146 (size "&$G8&"). Home location is "&$Q8&" ("&$R8&") when replenished.") -> Yes - 4 in stock at Store 0146 (size 8.5). Back room location A-01-2-02 (ZONE A / BAY 01 / SHELF 2 / BIN 02), Waist height. Back room 2 / sales floor 2.
A9: HB-4104220 | B9: 801963824529 | C9: ITM-700306 | D9: Brooks | E9: Ghost 17 | F9: Brooks Ghost 17 "Black/Ebony/Grey" Men's Shoe | G9: 9 | H9: =IFERROR(INDEX('Inventory Master'!$T$2:$T$525,MATCH($A9,'Inventory Master'!$A$2:$A$525,0)),0) -> 4 | I9: 1 | J9: =MAX(0,$H9-$I9) -> 3 | K9: =IF($H9>0,"In Stock","Out of Stock") -> In Stock | L9: A | M9: Men's Running & Training | N9: 1 | O9: 2 | P9: 3 | Q9: =$L9&"-"&TEXT($N9,"00")&"-"&$O9&"-"&TEXT($P9,"00") -> A-01-2-03 | R9: ="ZONE "&$L9&" / BAY "&TEXT($N9,"00")&" / SHELF "&$O9&" / BIN "&TEXT($P9,"00") -> ZONE A / BAY 01 / SHELF 2 / BIN 03 | S9: Waist height | T9: n/a | U9: 8 | V9: 46206 | W9: =IF($H9>0,"Yes - "&$H9&" in stock at Store 0146 (size "&$G9&"). Back room location "&$Q9&" ("&$R9&"), "&$S9&". Back room "&$J9&" / sales floor "&$I9&".","Not currently in stock at Store 0146 (size "&$G9&"). Home location is "&$Q9&" ("&$R9&") when replenished.") -> Yes - 4 in stock at Store 0146 (size 9). Back room location A-01-2-03 (ZONE A / BAY 01 / SHELF 2 / BIN 03), Waist height. Back room 3 / sales floor 1.
A10: HB-4104292 | B10: 896826526176 | C10: ITM-700316 | D10: Brooks | E10: Glycerin 22 | F10: Brooks Glycerin 22 "Grey/Navy/Blue" Men's Shoe | G10: 8.5 | H10: =IFERROR(INDEX('Inventory Master'!$T$2:$T$525,MATCH($A10,'Inventory Master'!$A$2:$A$525,0)),0) -> 2 | I10: 1 | J10: =MAX(0,$H10-$I10) -> 1 | K10: =IF($H10>0,"In Stock","Out of Stock") -> In Stock | L10: A | M10: Men's Running & Training | N10: 1 | O10: 3 | P10: 1 | Q10: =$L10&"-"&TEXT($N10,"00")&"-"&$O10&"-"&TEXT($P10,"00") -> A-01-3-01 | R10: ="ZONE "&$L10&" / BAY "&TEXT($N10,"00")&" / SHELF "&$O10&" / BIN "&TEXT($P10,"00") -> ZONE A / BAY 01 / SHELF 3 / BIN 01 | S10: Eye level | T10: n/a | U10: 9 | V10: 46204 | W10: =IF($H10>0,"Yes - "&$H10&" in stock at Store 0146 (size "&$G10&"). Back room location "&$Q10&" ("&$R10&"), "&$S10&". Back room "&$J10&" / sales floor "&$I10&".","Not currently in stock at Store 0146 (size "&$G10&"). Home location is "&$Q10&" ("&$R10&") when replenished.") -> Yes - 2 in stock at Store 0146 (size 8.5). Back room location A-01-3-01 (ZONE A / BAY 01 / SHELF 3 / BIN 01), Eye level. Back room 1 / sales floor 1.
A11: HB-4104298 | B11: 843556313047 | C11: ITM-700316 | D11: Brooks | E11: Glycerin 22 | F11: Brooks Glycerin 22 "Grey/Navy/Blue" Men's Shoe | G11: 9 | H11: =IFERROR(INDEX('Inventory Master'!$T$2:$T$525,MATCH($A11,'Inventory Master'!$A$2:$A$525,0)),0) -> 5 | I11: 2 | J11: =MAX(0,$H11-$I11) -> 3 | K11: =IF($H11>0,"In Stock","Out of Stock") -> In Stock | L11: A | M11: Men's Running & Training | N11: 1 | O11: 3 | P11: 2 | Q11: =$L11&"-"&TEXT($N11,"00")&"-"&$O11&"-"&TEXT($P11,"00") -> A-01-3-02 | R11: ="ZONE "&$L11&" / BAY "&TEXT($N11,"00")&" / SHELF "&$O11&" / BIN "&TEXT($P11,"00") -> ZONE A / BAY 01 / SHELF 3 / BIN 02 | S11: Eye level | T11: n/a | U11: 10 | V11: 46231 | W11: =IF($H11>0,"Yes - "&$H11&" in stock at Store 0146 (size "&$G11&"). Back room location "&$Q11&" ("&$R11&"), "&$S11&". Back room "&$J11&" / sales floor "&$I11&".","Not currently in stock at Store 0146 (size "&$G11&"). Home location is "&$Q11&" ("&$R11&") when replenished.") -> Yes - 5 in stock at Store 0146 (size 9). Back room location A-01-3-02 (ZONE A / BAY 01 / SHELF 3 / BIN 02), Eye level. Back room 3 / sales floor 2.
A12: HB-4104307 | B12: 826648843806 | C12: ITM-700316 | D12: Brooks | E12: Glycerin 22 | F12: Brooks Glycerin 22 "Grey/Navy/Blue" Men's Shoe | G12: 9.5 | H12: =IFERROR(INDEX('Inventory Master'!$T$2:$T$525,MATCH($A12,'Inventory Master'!$A$2:$A$525,0)),0) -> 0 | I12: 0 | J12: =MAX(0,$H12-$I12) -> 0 | K12: =IF($H12>0,"In Stock","Out of Stock") -> Out of Stock | L12: A | M12: Men's Running & Training | N12: 1 | O12: 3 | P12: 3 | Q12: =$L12&"-"&TEXT($N12,"00")&"-"&$O12&"-"&TEXT($P12,"00") -> A-01-3-03 | R12: ="ZONE "&$L12&" / BAY "&TEXT($N12,"00")&" / SHELF "&$O12&" / BIN "&TEXT($P12,"00") -> ZONE A / BAY 01 / SHELF 3 / BIN 03 | S12: Eye level | T12: n/a | U12: 11 | V12: 46205 | W12: =IF($H12>0,"Yes - "&$H12&" in stock at Store 0146 (size "&$G12&"). Back room location "&$Q12&" ("&$R12&"), "&$S12&". Back room "&$J12&" / sales floor "&$I12&".","Not currently in stock at Store 0146 (size "&$G12&"). Home location is "&$Q12&" ("&$R12&") when replenished.") -> Not currently in stock at Store 0146 (size 9.5). Home location is A-01-3-03 (ZONE A / BAY 01 / SHELF 3 / BIN 03) when replenished.
A13: HB-4104319 | B13: 853054309369 | C13: ITM-700316 | D13: Brooks | E13: Glycerin 22 | F13: Brooks Glycerin 22 "Grey/Navy/Blue" Men's Shoe | G13: 10 | H13: =IFERROR(INDEX('Inventory Master'!$T$2:$T$525,MATCH($A13,'Inventory Master'!$A$2:$A$525,0)),0) -> 3 | I13: 2 | J13: =MAX(0,$H13-$I13) -> 1 | K13: =IF($H13>0,"In Stock","Out of Stock") -> In Stock | L13: A | M13: Men's Running & Training | N13: 1 | O13: 3 | P13: 4 | Q13: =$L13&"-"&TEXT($N13,"00")&"-"&$O13&"-"&TEXT($P13,"00") -> A-01-3-04 | R13: ="ZONE "&$L13&" / BAY "&TEXT($N13,"00")&" / SHELF "&$O13&" / BIN "&TEXT($P13,"00") -> ZONE A / BAY 01 / SHELF 3 / BIN 04 | S13: Eye level | T13: n/a | U13: 12 | V13: 46211 | W13: =IF($H13>0,"Yes - "&$H13&" in stock at Store 0146 (size "&$G13&"). Back room location "&$Q13&" ("&$R13&"), "&$S13&". Back room "&$J13&" / sales floor "&$I13&".","Not currently in stock at Store 0146 (size "&$G13&"). Home location is "&$Q13&" ("&$R13&") when replenished.") -> Yes - 3 in stock at Store 0146 (size 10). Back room location A-01-3-04 (ZONE A / BAY 01 / SHELF 3 / BIN 04), Eye level. Back room 1 / sales floor 2.
... A444: HB-4102582 | B444: 877862873808 | C444: ITM-700225 | D444: adidas | E444: Adilette Comfort Slide | F444: adidas Adilette Comfort Slide "Core Black/White" Men's Shoe | G444: 13 | H444: =IFERROR(INDEX('Inventory Master'!$T$2:$T$525,MATCH($A444,'Inventory Master'!$A$2:$A$525,0)),0) -> 3 | I444: 2 | J444: =MAX(0,$H444-$I444) -> 1 | K444: =IF($H444>0,"In Stock","Out of Stock") -> In Stock | L444: F | M444: Sandals, Slides, Clogs & Boots | N444: 2 | O444: 2 | P444: 6 | Q444: =$L444&"-"&TEXT($N444,"00")&"-"&$O444&"-"&TEXT($P444,"00") -> F-02-2-06 | R444: ="ZONE "&$L444&" / BAY "&TEXT($N444,"00")&" / SHELF "&$O444&" / BIN "&TEXT($P444,"00") -> ZONE F / BAY 02 / SHELF 2 / BIN 06 | S444: Waist height | T444: n/a | U444: 443 | V444: 46218 | W444: =IF($H444>0,"Yes - "&$H444&" in stock at Store 0146 (size "&$G444&"). Back room location "&$Q444&" ("&$R444&"), "&$S444&". Back room "&$J444&" / sales floor "&$I444&".","Not currently in stock at Store 0146 (size "&$G444&"). Home location is "&$Q444&" ("&$R444&") when replenished.") -> Yes - 3 in stock at Store 0146 (size 13). Back room location F-02-2-06 (ZONE F / BAY 02 / SHELF 2 / BIN 06), Waist height. Back room 1 / sales floor 2.
A445: TOTAL | H445: =SUM(H2:H444) -> 1152 | I445: =SUM(I2:I444) -> 380 | J445: =SUM(J2:J444) -> 772 | K445: =COUNTIF(K2:K444,"In Stock")&" of "&443&" SKUs in stock" -> 354 of 443 SKUs in stock
A447: Location ID grammar: ZONE - BAY - SHELF - BIN (e.g. C-07-3-04 = Zone C, Bay 07, Shelf 3, Bin 04). Every size of a given style shares one shelf, running left to right in ascending size order, so a whole style can be pulled from a single shelf. Rows are sorted in pick-walk sequence.

Sheet Style Master
A1: Item ID | B1: Manufacturer | C1: Brand | D1: Model | E1: Style Number | F1: Product Description | G1: Category | H1: Sub-Category | I1: Gender | J1: Color | K1: Season | L1: Lifecycle Status | M1: MSRP | N1: Current Retail | O1: Unit Cost | P1: Assortment Tier | Q1: Stores Assorted | R1: SKUs (Sizes) | S1: Total Units On Hand | T1: On-Hand Retail Value
A2: ITM-700305 | B2: ASICS Corporation | C2: ASICS | D2: GEL-1130 | E2: 1091B332-674 | F2: ASICS GEL-1130 "White/Clay Canyon" Unisex Shoe | G2: Casual | H2: Retro Running | I2: Unisex | J2: White/Clay Canyon | K2: SP26 | L2: Clearance | M2: 109.99 | N2: 70.99 | O2: 57.65 | P2: B (3 of 4 stores) | Q2: 3 | R2: =COUNTIF('Inventory Master'!$C$2:$C$525,$A2) -> 3 | S2: =SUMIF('Inventory Master'!$C$2:$C$525,$A2,'Inventory Master'!$X$2:$X$525) -> 26 | T2: =SUMIF('Inventory Master'!$C$2:$C$525,$A2,'Inventory Master'!$Z$2:$Z$525) -> 1845.74
A3: ITM-700301 | B3: ASICS Corporation | C3: ASICS | D3: GEL-CONTEND 9 | E3: 1001B908-716 | F3: ASICS GEL-CONTEND 9 "White/Rose" Women's Shoe | G3: Running | H3: Entry Cushion | I3: Women | J3: White/Rose | K3: SP26 | L3: Clearance | M3: 69.99 | N3: 41.99 | O3: 36.27 | P3: D (1 of 4 stores) | Q3: 1 | R3: =COUNTIF('Inventory Master'!$C$2:$C$525,$A3) -> 4 | S3: =SUMIF('Inventory Master'!$C$2:$C$525,$A3,'Inventory Master'!$X$2:$X$525) -> 5 | T3: =SUMIF('Inventory Master'!$C$2:$C$525,$A3,'Inventory Master'!$Z$2:$Z$525) -> 209.95
A4: ITM-700298 | B4: ASICS Corporation | C4: ASICS | D4: GEL-EXCITE 11 | E4: 1069B692-193 | F4: ASICS GEL-EXCITE 11 "Black/Carrier Grey" Men's Shoe | G4: Running | H4: Entry Cushion | I4: Men | J4: Black/Carrier Grey | K4: SP26 | L4: Active | M4: 79.99 | N4: 79.99 | O4: 40.55 | P4: B (3 of 4 stores) | Q4: 3 | R4: =COUNTIF('Inventory Master'!$C$2:$C$525,$A4) -> 5 | S4: =SUMIF('Inventory Master'!$C$2:$C$525,$A4,'Inventory Master'!$X$2:$X$525) -> 40 | T4: =SUMIF('Inventory Master'!$C$2:$C$525,$A4,'Inventory Master'!$Z$2:$Z$525) -> 3199.6
A5: ITM-700293 | B5: ASICS Corporation | C5: ASICS | D5: GEL-KAYANO 32 | E5: 1061B874-346 | F5: ASICS GEL-KAYANO 32 "Black/Graphite Grey" Men's Shoe | G5: Running | H5: Stability | I5: Men | J5: Black/Graphite Grey | K5: FA25 | L5: Clearance | M5: 169.99 | N5: 101.99 | O5: 84.77 | P5: D (1 of 4 stores) | Q5: 1 | R5: =COUNTIF('Inventory Master'!$C$2:$C$525,$A5) -> 5 | S5: =SUMIF('Inventory Master'!$C$2:$C$525,$A5,'Inventory Master'!$X$2:$X$525) -> 16 | T5: =SUMIF('Inventory Master'!$C$2:$C$525,$A5,'Inventory Master'!$Z$2:$Z$525) -> 1631.84
A6: ITM-700294 | B6: ASICS Corporation | C6: ASICS | D6: GEL-NIMBUS 28 | E6: 1032B092-817 | F6: ASICS GEL-NIMBUS 28 "Cloud Grey/Sky" Women's Shoe | G6: Running | H6: Premium Cushion | I6: Women | J6: Cloud Grey/Sky | K6: SP26 | L6: Active | M6: 179.99 | N6: 179.99 | O6: 97.26 | P6: B (3 of 4 stores) | Q6: 3 | R6: =COUNTIF('Inventory Master'!$C$2:$C$525,$A6) -> 5 | S6: =SUMIF('Inventory Master'!$C$2:$C$525,$A6,'Inventory Master'!$X$2:$X$525) -> 35 | T6: =SUMIF('Inventory Master'!$C$2:$C$525,$A6,'Inventory Master'!$Z$2:$Z$525) -> 6299.65
A7: ITM-700302 | B7: ASICS Corporation | C7: ASICS | D7: GEL-NYC | E7: 1024B246-768 | F7: ASICS GEL-NYC "Oyster Grey/Clay Grey" Unisex Shoe | G7: Casual | H7: Retro Running | I7: Unisex | J7: Oyster Grey/Clay Grey | K7: SP26 | L7: Active | M7: 149.99 | N7: 149.99 | O7: 80.52 | P7: A (4 of 4 stores) | Q7: 4 | R7: =COUNTIF('Inventory Master'!$C$2:$C$525,$A7) -> 3 | S7: =SUMIF('Inventory Master'!$C$2:$C$525,$A7,'Inventory Master'!$X$2:$X$525) -> 31 | T7: =SUMIF('Inventory Master'!$C$2:$C$525,$A7,'Inventory Master'!$Z$2:$Z$525) -> 4649.69
A8: ITM-700402 | B8: Birkenstock GmbH | C8: Birkenstock | D8: Arizona Essentials EVA | E8: 4242715 | F8: Birkenstock Arizona Essentials EVA "Black" Unisex Shoe | G8: Sandals | H8: Sandals | I8: Unisex | J8: Black | K8: HO25 | L8: Active | M8: 54.99 | N8: 54.99 | O8: 26.61 | P8: C (2 of 4 stores) | Q8: 2 | R8: =COUNTIF('Inventory Master'!$C$2:$C$525,$A8) -> 6 | S8: =SUMIF('Inventory Master'!$C$2:$C$525,$A8,'Inventory Master'!$X$2:$X$525) -> 36 | T8: =SUMIF('Inventory Master'!$C$2:$C$525,$A8,'Inventory Master'!$Z$2:$Z$525) -> 1979.64
A9: ITM-700314 | B9: Brooks Sports, Inc. | C9: Brooks | D9: Adrenaline GTS 24 | E9: 110377-1D-913 | F9: Brooks Adrenaline GTS 24 "Grey/Lilac/Silver" Women's Shoe | G9: Running | H9: Stability | I9: Women | J9: Grey/Lilac/Silver | K9: SP26 | L9: Active | M9: 149.99 | N9: 149.99 | O9: 72.34 | P9: A (4 of 4 stores) | Q9: 4 | R9: =COUNTIF('Inventory Master'!$C$2:$C$525,$A9) -> 3 | S9: =SUMIF('Inventory Master'!$C$2:$C$525,$A9,'Inventory Master'!$X$2:$X$525) -> 30 | T9: =SUMIF('Inventory Master'!$C$2:$C$525,$A9,'Inventory Master'!$Z$2:$Z$525) -> 4499.7
A10: ITM-700306 | B10: Brooks Sports, Inc. | C10: Brooks | D10: Ghost 17 | E10: 110390-1D-470 | F10: Brooks Ghost 17 "Black/Ebony/Grey" Men's Shoe | G10: Running | H10: Neutral Cushion | I10: Men | J10: Black/Ebony/Grey | K10: FA25 | L10: Active | M10: 149.99 | N10: 149.99 | O10: 76.29 | P10: A (4 of 4 stores) | Q10: 4 | R10: =COUNTIF('Inventory Master'!$C$2:$C$525,$A10) -> 3 | S10: =SUMIF('Inventory Master'!$C$2:$C$525,$A10,'Inventory Master'!$X$2:$X$525) -> 30 | T10: =SUMIF('Inventory Master'!$C$2:$C$525,$A10,'Inventory Master'!$Z$2:$Z$525) -> 4499.7
A11: ITM-700310 | B11: Brooks Sports, Inc. | C11: Brooks | D11: Ghost 17 | E11: 110343-1D-175 | F11: Brooks Ghost 17 "White/Coral/Peach" Women's Shoe | G11: Running | H11: Neutral Cushion | I11: Women | J11: White/Coral/Peach | K11: FA26 | L11: Pre-Season | M11: 149.99 | N11: 149.99 | O11: 73.89 | P11: B (3 of 4 stores) | Q11: 3 | R11: =COUNTIF('Inventory Master'!$C$2:$C$525,$A11) -> 3 | S11: =SUMIF('Inventory Master'!$C$2:$C$525,$A11,'Inventory Master'!$X$2:$X$525) -> 31 | T11: =SUMIF('Inventory Master'!$C$2:$C$525,$A11,'Inventory Master'!$Z$2:$Z$525) -> 4649.69
A12: ITM-700316 | B12: Brooks Sports, Inc. | C12: Brooks | D12: Glycerin 22 | E12: 110320-1D-271 | F12: Brooks Glycerin 22 "Grey/Navy/Blue" Men's Shoe | G12: Running | H12: Premium Cushion | I12: Men | J12: Grey/Navy/Blue | K12: SU26 | L12: Active | M12: 169.99 | N12: 169.99 | O12: 89.36 | P12: C (2 of 4 stores) | Q12: 2 | R12: =COUNTIF('Inventory Master'!$C$2:$C$525,$A12) -> 6 | S12: =SUMIF('Inventory Master'!$C$2:$C$525,$A12,'Inventory Master'!$X$2:$X$525) -> 45 | T12: =SUMIF('Inventory Master'!$C$2:$C$525,$A12,'Inventory Master'!$Z$2:$Z$525) -> 7649.55
A13: ITM-700359 | B13: Converse, Inc. | C13: Converse | D13: Chuck 70 Low | E13: M9038V | F13: Converse Chuck 70 Low "Parchment/Egret" Unisex Shoe | G13: Casual | H13: Canvas / Skate | I13: Unisex | J13: Parchment/Egret | K13: SP26 | L13: Active | M13: 89.99 | N13: 89.99 | O13: 44.27 | P13: A (4 of 4 stores) | Q13: 4 | R13: =COUNTIF('Inventory Master'!$C$2:$C$525,$A13) -> 5 | S13: =SUMIF('Inventory Master'!$C$2:$C$525,$A13,'Inventory Master'!$X$2:$X$525) -> 46 | T13: =SUMIF('Inventory Master'!$C$2:$C$525,$A13,'Inventory Master'!$Z$2:$Z$525) -> 4139.54
... A119: ITM-700200 | B119: adidas AG | C119: adidas Originals | D119: Superstar | E119: UP8227 | F119: adidas Originals Superstar "White/Core Black" Big Kids' Shoe | G119: Casual | H119: Court / Lifestyle | I119: Big Kids | J119: White/Core Black | K119: FA26 | L119: Active | M119: 74.99 | N119: 74.99 | O119: 39.21 | P119: A (4 of 4 stores) | Q119: 4 | R119: =COUNTIF('Inventory Master'!$C$2:$C$525,$A119) -> 5 | S119: =SUMIF('Inventory Master'!$C$2:$C$525,$A119,'Inventory Master'!$X$2:$X$525) -> 58 | T119: =SUMIF('Inventory Master'!$C$2:$C$525,$A119,'Inventory Master'!$Z$2:$Z$525) -> 4349.42
A120: TOTAL | R120: =SUM(R2:R119) -> 524 | S120: =SUM(S2:S119) -> 4021 | T120: =SUM(T2:T119) -> 446453.79

Sheet Store Summary
A1: Store Summary — Units On Hand
A2: Live SUMIFS against Inventory Master. Filtering Inventory Master does not change these figures.
A4: Units On Hand by Brand
A5: Brand | B5: Store 0146 | C5: Store 1382 | D5: Store 2071 | E5: Store 3719 | F5: All Stores | G5: % of Chain
A6: ASICS | B6: =SUMIF('Inventory Master'!$E$2:$E$525,$A6,'Inventory Master'!$T$2:$T$525) -> 37 | C6: =SUMIF('Inventory Master'!$E$2:$E$525,$A6,'Inventory Master'!$U$2:$U$525) -> 27 | D6: =SUMIF('Inventory Master'!$E$2:$E$525,$A6,'Inventory Master'!$V$2:$V$525) -> 75 | E6: =SUMIF('Inventory Master'!$E$2:$E$525,$A6,'Inventory Master'!$W$2:$W$525) -> 14 | F6: =SUM(B6:E6) -> 153 | G6: =IFERROR(F6/F$28,0) -> 0.038050236
A7: Birkenstock | B7: =SUMIF('Inventory Master'!$E$2:$E$525,$A7,'Inventory Master'!$T$2:$T$525) -> 11 | C7: =SUMIF('Inventory Master'!$E$2:$E$525,$A7,'Inventory Master'!$U$2:$U$525) -> 0 | D7: =SUMIF('Inventory Master'!$E$2:$E$525,$A7,'Inventory Master'!$V$2:$V$525) -> 25 | E7: =SUMIF('Inventory Master'!$E$2:$E$525,$A7,'Inventory Master'!$W$2:$W$525) -> 0 | F7: =SUM(B7:E7) -> 36 | G7: =IFERROR(F7/F$28,0) -> 0.0089529968
A8: Brooks | B8: =SUMIF('Inventory Master'!$E$2:$E$525,$A8,'Inventory Master'!$T$2:$T$525) -> 36 | C8: =SUMIF('Inventory Master'!$E$2:$E$525,$A8,'Inventory Master'!$U$2:$U$525) -> 23 | D8: =SUMIF('Inventory Master'!$E$2:$E$525,$A8,'Inventory Master'!$V$2:$V$525) -> 56 | E8: =SUMIF('Inventory Master'!$E$2:$E$525,$A8,'Inventory Master'!$W$2:$W$525) -> 21 | F8: =SUM(B8:E8) -> 136 | G8: =IFERROR(F8/F$28,0) -> 0.033822432
A9: Converse | B9: =SUMIF('Inventory Master'!$E$2:$E$525,$A9,'Inventory Master'!$T$2:$T$525) -> 42 | C9: =SUMIF('Inventory Master'!$E$2:$E$525,$A9,'Inventory Master'!$U$2:$U$525) -> 8 | D9: =SUMIF('Inventory Master'!$E$2:$E$525,$A9,'Inventory Master'!$V$2:$V$525) -> 68 | E9: =SUMIF('Inventory Master'!$E$2:$E$525,$A9,'Inventory Master'!$W$2:$W$525) -> 7 | F9: =SUM(B9:E9) -> 125 | G9: =IFERROR(F9/F$28,0) -> 0.031086794
A10: Crocs | B10: =SUMIF('Inventory Master'!$E$2:$E$525,$A10,'Inventory Master'!$T$2:$T$525) -> 32 | C10: =SUMIF('Inventory Master'!$E$2:$E$525,$A10,'Inventory Master'!$U$2:$U$525) -> 17 | D10: =SUMIF('Inventory Master'!$E$2:$E$525,$A10,'Inventory Master'!$V$2:$V$525) -> 41 | E10: =SUMIF('Inventory Master'!$E$2:$E$525,$A10,'Inventory Master'!$W$2:$W$525) -> 20 | F10: =SUM(B10:E10) -> 110 | G10: =IFERROR(F10/F$28,0) -> 0.027356379
A11: Fila | B11: =SUMIF('Inventory Master'!$E$2:$E$525,$A11,'Inventory Master'!$T$2:$T$525) -> 0 | C11: =SUMIF('Inventory Master'!$E$2:$E$525,$A11,'Inventory Master'!$U$2:$U$525) -> 0 | D11: =SUMIF('Inventory Master'!$E$2:$E$525,$A11,'Inventory Master'!$V$2:$V$525) -> 12 | E11: =SUMIF('Inventory Master'!$E$2:$E$525,$A11,'Inventory Master'!$W$2:$W$525) -> 0 | F11: =SUM(B11:E11) -> 12 | G11: =IFERROR(F11/F$28,0) -> 0.0029843323
A12: HOKA | B12: =SUMIF('Inventory Master'!$E$2:$E$525,$A12,'Inventory Master'!$T$2:$T$525) -> 43 | C12: =SUMIF('Inventory Master'!$E$2:$E$525,$A12,'Inventory Master'!$U$2:$U$525) -> 28 | D12: =SUMIF('Inventory Master'!$E$2:$E$525,$A12,'Inventory Master'!$V$2:$V$525) -> 54 | E12: =SUMIF('Inventory Master'!$E$2:$E$525,$A12,'Inventory Master'!$W$2:$W$525) -> 12 | F12: =SUM(B12:E12) -> 137 | G12: =IFERROR(F12/F$28,0) -> 0.034071127
A13: Jordan | B13: =SUMIF('Inventory Master'!$E$2:$E$525,$A13,'Inventory Master'!$T$2:$T$525) -> 78 | C13: =SUMIF('Inventory Master'!$E$2:$E$525,$A13,'Inventory Master'!$U$2:$U$525) -> 34 | D13: =SUMIF('Inventory Master'!$E$2:$E$525,$A13,'Inventory Master'!$V$2:$V$525) -> 146 | E13: =SUMIF('Inventory Master'!$E$2:$E$525,$A13,'Inventory Master'!$W$2:$W$525) -> 32 | F13: =SUM(B13:E13) -> 290 | G13: =IFERROR(F13/F$28,0) -> 0.072121363
A14: Mizuno | B14: =SUMIF('Inventory Master'!$E$2:$E$525,$A14,'Inventory Master'!$T$2:$T$525) -> 17 | C14: =SUMIF('Inventory Master'!$E$2:$E$525,$A14,'Inventory Master'!$U$2:$U$525) -> 3 | D14: =SUMIF('Inventory Master'!$E$2:$E$525,$A14,'Inventory Master'!$V$2:$V$525) -> 24 | E14: =SUMIF('Inventory Master'!$E$2:$E$525,$A14,'Inventory Master'!$W$2:$W$525) -> 0 | F14: =SUM(B14:E14) -> 44 | G14: =IFERROR(F14/F$28,0) -> 0.010942552
A15: New Balance | B15: =SUMIF('Inventory Master'!$E$2:$E$525,$A15,'Inventory Master'!$T$2:$T$525) -> 111 | C15: =SUMIF('Inventory Master'!$E$2:$E$525,$A15,'Inventory Master'!$U$2:$U$525) -> 77 | D15: =SUMIF('Inventory Master'!$E$2:$E$525,$A15,'Inventory Master'!$V$2:$V$525) -> 187 | E15: =SUMIF('Inventory Master'!$E$2:$E$525,$A15,'Inventory Master'!$W$2:$W$525) -> 40 | F15: =SUM(B15:E15) -> 415 | G15: =IFERROR(F15/F$28,0) -> 0.10320816
A16: Nike | B16: =SUMIF('Inventory Master'!$E$2:$E$525,$A16,'Inventory Master'!$T$2:$T$525) -> 263 | C16: =SUMIF('Inventory Master'!$E$2:$E$525,$A16,'Inventory Master'!$U$2:$U$525) -> 149 | D16: =SUMIF('Inventory Master'!$E$2:$E$525,$A16,'Inventory Master'!$V$2:$V$525) -> 394 | E16: =SUMIF('Inventory Master'!$E$2:$E$525,$A16,'Inventory Master'!$W$2:$W$525) -> 70 | F16: =SUM(B16:E16) -> 876 | G16: =IFERROR(F16/F$28,0) -> 0.21785625
A17: On | B17: =SUMIF('Inventory Master'!$E$2:$E$525,$A17,'Inventory Master'!$T$2:$T$525) -> 21 | C17: =SUMIF('Inventory Master'!$E$2:$E$525,$A17,'Inventory Master'!$U$2:$U$525) -> 20 | D17: =SUMIF('Inventory Master'!$E$2:$E$525,$A17,'Inventory Master'!$V$2:$V$525) -> 41 | E17: =SUMIF('Inventory Master'!$E$2:$E$525,$A17,'Inventory Master'!$W$2:$W$525) -> 6 | F17: =SUM(B17:E17) -> 88 | G17: =IFERROR(F17/F$28,0) -> 0.021885103
... A27: adidas Originals | B27: =SUMIF('Inventory Master'!$E$2:$E$525,$A27,'Inventory Master'!$T$2:$T$525) -> 90 | C27: =SUMIF('Inventory Master'!$E$2:$E$525,$A27,'Inventory Master'!$U$2:$U$525) -> 77 | D27: =SUMIF('Inventory Master'!$E$2:$E$525,$A27,'Inventory Master'!$V$2:$V$525) -> 136 | E27: =SUMIF('Inventory Master'!$E$2:$E$525,$A27,'Inventory Master'!$W$2:$W$525) -> 36 | F27: =SUM(B27:E27) -> 339 | G27: =IFERROR(F27/F$28,0) -> 0.084307386
A28: Total | B28: =SUM(B6:B27) -> 1152 | C28: =SUM(C6:C27) -> 663 | D28: =SUM(D6:D27) -> 1831 | E28: =SUM(E6:E27) -> 375 | F28: =SUM(F6:F27) -> 4021 | G28: =IFERROR(F28/F28,0) -> 1
A31: Units On Hand by Category
A32: Category | B32: Store 0146 | C32: Store 1382 | D32: Store 2071 | E32: Store 3719 | F32: All Stores | G32: % of Chain
A33: Baseball | B33: =SUMIF('Inventory Master'!$I$2:$I$525,$A33,'Inventory Master'!$T$2:$T$525) -> 12 | C33: =SUMIF('Inventory Master'!$I$2:$I$525,$A33,'Inventory Master'!$U$2:$U$525) -> 3 | D33: =SUMIF('Inventory Master'!$I$2:$I$525,$A33,'Inventory Master'!$V$2:$V$525) -> 20 | E33: =SUMIF('Inventory Master'!$I$2:$I$525,$A33,'Inventory Master'!$W$2:$W$525) -> 0 | F33: =SUM(B33:E33) -> 35 | G33: =IFERROR(F33/F$39,0) -> 0.0087043024
A34: Basketball | B34: =SUMIF('Inventory Master'!$I$2:$I$525,$A34,'Inventory Master'!$T$2:$T$525) -> 106 | C34: =SUMIF('Inventory Master'!$I$2:$I$525,$A34,'Inventory Master'!$U$2:$U$525) -> 98 | D34: =SUMIF('Inventory Master'!$I$2:$I$525,$A34,'Inventory Master'!$V$2:$V$525) -> 176 | E34: =SUMIF('Inventory Master'!$I$2:$I$525,$A34,'Inventory Master'!$W$2:$W$525) -> 22 | F34: =SUM(B34:E34) -> 402 | G34: =IFERROR(F34/F$39,0) -> 0.099975131
A35: Casual | B35: =SUMIF('Inventory Master'!$I$2:$I$525,$A35,'Inventory Master'!$T$2:$T$525) -> 619 | C35: =SUMIF('Inventory Master'!$I$2:$I$525,$A35,'Inventory Master'!$U$2:$U$525) -> 315 | D35: =SUMIF('Inventory Master'!$I$2:$I$525,$A35,'Inventory Master'!$V$2:$V$525) -> 939 | E35: =SUMIF('Inventory Master'!$I$2:$I$525,$A35,'Inventory Master'!$W$2:$W$525) -> 204 | F35: =SUM(B35:E35) -> 2077 | G35: =IFERROR(F35/F$39,0) -> 0.51653817
A36: Running | B36: =SUMIF('Inventory Master'!$I$2:$I$525,$A36,'Inventory Master'!$T$2:$T$525) -> 315 | C36: =SUMIF('Inventory Master'!$I$2:$I$525,$A36,'Inventory Master'!$U$2:$U$525) -> 200 | D36: =SUMIF('Inventory Master'!$I$2:$I$525,$A36,'Inventory Master'!$V$2:$V$525) -> 523 | E36: =SUMIF('Inventory Master'!$I$2:$I$525,$A36,'Inventory Master'!$W$2:$W$525) -> 122 | F36: =SUM(B36:E36) -> 1160 | G36: =IFERROR(F36/F$39,0) -> 0.28848545
A37: Sandals | B37: =SUMIF('Inventory Master'!$I$2:$I$525,$A37,'Inventory Master'!$T$2:$T$525) -> 79 | C37: =SUMIF('Inventory Master'!$I$2:$I$525,$A37,'Inventory Master'!$U$2:$U$525) -> 30 | D37: =SUMIF('Inventory Master'!$I$2:$I$525,$A37,'Inventory Master'!$V$2:$V$525) -> 111 | E37: =SUMIF('Inventory Master'!$I$2:$I$525,$A37,'Inventory Master'!$W$2:$W$525) -> 21 | F37: =SUM(B37:E37) -> 241 | G37: =IFERROR(F37/F$39,0) -> 0.059935339
A38: Training | B38: =SUMIF('Inventory Master'!$I$2:$I$525,$A38,'Inventory Master'!$T$2:$T$525) -> 21 | C38: =SUMIF('Inventory Master'!$I$2:$I$525,$A38,'Inventory Master'!$U$2:$U$525) -> 17 | D38: =SUMIF('Inventory Master'!$I$2:$I$525,$A38,'Inventory Master'!$V$2:$V$525) -> 62 | E38: =SUMIF('Inventory Master'!$I$2:$I$525,$A38,'Inventory Master'!$W$2:$W$525) -> 6 | F38: =SUM(B38:E38) -> 106 | G38: =IFERROR(F38/F$39,0) -> 0.026361602
A39: Total | B39: =SUM(B33:B38) -> 1152 | C39: =SUM(C33:C38) -> 663 | D39: =SUM(D33:D38) -> 1831 | E39: =SUM(E33:E38) -> 375 | F39: =SUM(F33:F38) -> 4021 | G39: =IFERROR(F39/F39,0) -> 1
A42: Units On Hand by Gender / Size Range
A43: Gender | B43: Store 0146 | C43: Store 1382 | D43: Store 2071 | E43: Store 3719 | F43: All Stores | G43: % of Chain
A44: Big Kids | B44: =SUMIF('Inventory Master'!$K$2:$K$525,$A44,'Inventory Master'!$T$2:$T$525) -> 109 | C44: =SUMIF('Inventory Master'!$K$2:$K$525,$A44,'Inventory Master'!$U$2:$U$525) -> 53 | D44: =SUMIF('Inventory Master'!$K$2:$K$525,$A44,'Inventory Master'!$V$2:$V$525) -> 170 | E44: =SUMIF('Inventory Master'!$K$2:$K$525,$A44,'Inventory Master'!$W$2:$W$525) -> 36 | F44: =SUM(B44:E44) -> 368 | G44: =IFERROR(F44/F$49,0) -> 0.091519523
A45: Little Kids | B45: =SUMIF('Inventory Master'!$K$2:$K$525,$A45,'Inventory Master'!$T$2:$T$525) -> 35 | C45: =SUMIF('Inventory Master'!$K$2:$K$525,$A45,'Inventory Master'!$U$2:$U$525) -> 14 | D45: =SUMIF('Inventory Master'!$K$2:$K$525,$A45,'Inventory Master'!$V$2:$V$525) -> 60 | E45: =SUMIF('Inventory Master'!$K$2:$K$525,$A45,'Inventory Master'!$W$2:$W$525) -> 29 | F45: =SUM(B45:E45) -> 138 | G45: =IFERROR(F45/F$49,0) -> 0.034319821
A46: Men | B46: =SUMIF('Inventory Master'!$K$2:$K$525,$A46,'Inventory Master'!$T$2:$T$525) -> 556 | C46: =SUMIF('Inventory Master'!$K$2:$K$525,$A46,'Inventory Master'!$U$2:$U$525) -> 339 | D46: =SUMIF('Inventory Master'!$K$2:$K$525,$A46,'Inventory Master'!$V$2:$V$525) -> 924 | E46: =SUMIF('Inventory Master'!$K$2:$K$525,$A46,'Inventory Master'!$W$2:$W$525) -> 168 | F46: =SUM(B46:E46) -> 1987 | G46: =IFERROR(F46/F$49,0) -> 0.49415568
A47: Unisex | B47: =SUMIF('Inventory Master'!$K$2:$K$525,$A47,'Inventory Master'!$T$2:$T$525) -> 147 | C47: =SUMIF('Inventory Master'!$K$2:$K$525,$A47,'Inventory Master'!$U$2:$U$525) -> 51 | D47: =SUMIF('Inventory Master'!$K$2:$K$525,$A47,'Inventory Master'!$V$2:$V$525) -> 199 | E47: =SUMIF('Inventory Master'!$K$2:$K$525,$A47,'Inventory Master'!$W$2:$W$525) -> 54 | F47: =SUM(B47:E47) -> 451 | G47: =IFERROR(F47/F$49,0) -> 0.11216115
A48: Women | B48: =SUMIF('Inventory Master'!$K$2:$K$525,$A48,'Inventory Master'!$T$2:$T$525) -> 305 | C48: =SUMIF('Inventory Master'!$K$2:$K$525,$A48,'Inventory Master'!$U$2:$U$525) -> 206 | D48: =SUMIF('Inventory Master'!$K$2:$K$525,$A48,'Inventory Master'!$V$2:$V$525) -> 478 | E48: =SUMIF('Inventory Master'!$K$2:$K$525,$A48,'Inventory Master'!$W$2:$W$525) -> 88 | F48: =SUM(B48:E48) -> 1077 | G48: =IFERROR(F48/F$49,0) -> 0.26784382
A49: Total | B49: =SUM(B44:B48) -> 1152 | C49: =SUM(C44:C48) -> 663 | D49: =SUM(D44:D48) -> 1831 | E49: =SUM(E44:E48) -> 375 | F49: =SUM(F44:F48) -> 4021 | G49: =IFERROR(F49/F49,0) -> 1
